Workbook

Sheet Quotation
A1: QUOTATION — Renovation and Extension, 53 Shlonsky St., Haifa
A2: Employer: Zohar Mor Yosef and Rami Dana | Contractor: [Contractor name] | Date: 14/10/2026 | Quotation no.: [__]
A3: All amounts in GBP (£), excluding VAT, price base October 2026. Unit rates include the contractor's overheads and profit (15%).
A5: Item | B5: Description | C5: Scope | D5: Unit | E5: Qty | F5: Unit rate | G5: Amount | H5: Remarks
A6: Chapter 1 — Preparation and Site Establishment
A7: 01.01 | B7: Site establishment | C7: Setting up work and storage areas, workers' facilities and access coordination. | D7: lot | E7: 1 | F7: 2580 | G7: =IF(AND(ISNUMBER(E7),ISNUMBER(F7)),ROUND(E7*F7,2),"") -> 2580
A8: 01.02 | B8: Site hoarding, signage and safety | C8: Temporary hoarding, site and hazard signage, and the safety measures required for the works. | D8: lot | E8: 1 | F8: 1290 | G8: =IF(AND(ISNUMBER(E8),ISNUMBER(F8)),ROUND(E8*F8,2),"") -> 1290
A9: 01.03 | B9: Temporary water connection | C9: Temporary water connection from the approved source, tested. | D9: lot | E9: 1 | F9: 484 | G9: =IF(AND(ISNUMBER(E9),ISNUMBER(F9)),ROUND(E9*F9,2),"") -> 484
A10: 01.04 | B10: Temporary electrical connection | C10: Temporary power connection by a licensed electrician, with protection and testing. | D10: lot | E10: 1 | F10: 970 | G10: =IF(AND(ISNUMBER(E10),ISNUMBER(F10)),ROUND(E10*F10,2),"") -> 970
A11: 01.05 | B11: Protection of existing elements | C11: Protective covers for floors, openings, windows, stairs, railings, walls and plants to be retained. | D11: lot | E11: 1 | F11: 1610 | G11: =IF(AND(ISNUMBER(E11),ISNUMBER(F11)),ROUND(E11*F11,2),"") -> 1610
A12: 01.06 | B12: Survey, verification and laser setting-out | C12: Survey of the existing building, verification against architectural and services drawings, setting-out of positions and levels. | D12: lot | E12: 1 | F12: 970 | G12: =IF(AND(ISNUMBER(E12),ISNUMBER(F12)),ROUND(E12*F12,2),"") -> 970
A13: 01.07 | B13: Waste skip and waste collection area | C13: Skip placement and a waste collection area; removal of waste to a licensed site. | D13: lot | E13: 1 | F13: 2900 | G13: =IF(AND(ISNUMBER(E13),ISNUMBER(F13)),ROUND(E13*F13,2),"") -> 2900
A14: 01.08 | B14: Ongoing site cleaning | C14: Periodic cleaning of work areas and passages throughout the works. | D14: lot | E14: 1 | F14: 2900 | G14: =IF(AND(ISNUMBER(E14),ISNUMBER(F14)),ROUND(E14*F14,2),"") -> 2900
A15: 01.09 | B15: External scaffolding | C15: Erection, rental for the works period (about 4.5 months), maintenance and removal of compliant external scaffolding around the facades, for sawing the decorative concrete frames and the facade plaster works. | D15: m² | E15: 225 | F15: 40.5 | G15: =IF(AND(ISNUMBER(E15),ISNUMBER(F15)),ROUND(E15*F15,2),"") -> 9112.5 | H15: Provisional quantity – remeasured
A16: Total – Chapter 1 | G16: =IF(COUNT(G7:G15)=0,"",SUM(G7:G15)) -> 22816.5
A18: Chapter 2 — Demolition, Removals and Disposal
A19: 02.01 | B19: Demolition of walls and partitions – basement | C19: Demolition of existing walls and partitions per demolition drawings. | D19: m² | E19: 62 | F19: 38.5 | G19: =IF(AND(ISNUMBER(E19),ISNUMBER(F19)),ROUND(E19*F19,2),"") -> 2387
A20: 02.02 | B20: Demolition of walls and partitions – ground floor | C20: Demolition of existing walls and partitions per demolition drawings. | D20: m² | E20: 51 | F20: 38.5 | G20: =IF(AND(ISNUMBER(E20),ISNUMBER(F20)),ROUND(E20*F20,2),"") -> 1963.5
A21: 02.03 | B21: Demolition of walls and partitions – first floor | C21: Demolition of existing walls and partitions per demolition drawings. | D21: m² | E21: 85 | F21: 38.5 | G21: =IF(AND(ISNUMBER(E21),ISNUMBER(F21)),ROUND(E21*F21,2),"") -> 3272.5
A22: 02.04 | B22: Removal of existing gypsum ceilings | C22: Removal of existing suspended gypsum ceilings. | D22: m² | E22: 10 | F22: 16 | G22: =IF(AND(ISNUMBER(E22),ISNUMBER(F22)),ROUND(E22*F22,2),"") -> 160
A23: 02.05 | B23: Removal of existing flooring | C23: Removal of existing floor finishes. | D23: m² | E23: 40 | F23: 29 | G23: =IF(AND(ISNUMBER(E23),ISNUMBER(F23)),ROUND(E23*F23,2),"") -> 1160
A24: 02.06 | B24: Removal of existing kitchen cabinets | C24: Removal of existing kitchen cabinets, complete. | D24: lot | E24: 1 | F24: 650 | G24: =IF(AND(ISNUMBER(E24),ISNUMBER(F24)),ROUND(E24*F24,2),"") -> 650
A25: 02.07 | B25: Removal of other existing joinery | C25: Removal of other existing cabinets and joinery. | D25: pcs | E25: 1 | F25: 810 | G25: =IF(AND(ISNUMBER(E25),ISNUMBER(F25)),ROUND(E25*F25,2),"") -> 810
A26: 02.08 | B26: Removal of existing aluminium windows and shutters | C26: Complete removal of existing aluminium windows and roller shutters. | D26: lot | E26: 1 | F26: 1940 | G26: =IF(AND(ISNUMBER(E26),ISNUMBER(F26)),ROUND(E26*F26,2),"") -> 1940
A27: 02.09 | B27: Removal of interior and entrance doors and frames | C27: Complete removal of existing interior and entrance doors and frames. | D27: lot | E27: 1 | F27: 1130 | G27: =IF(AND(ISNUMBER(E27),ISNUMBER(F27)),ROUND(E27*F27,2),"") -> 1130
A28: 02.10 | B28: Removal of bathrooms, WCs and sanitary ware | C28: Complete removal of existing bathrooms, WCs and sanitary fixtures. | D28: lot | E28: 1 | F28: 2580 | G28: =IF(AND(ISNUMBER(E28),ISNUMBER(F28)),ROUND(E28*F28,2),"") -> 2580
A29: 02.11 | B29: Removal of electrical points, accessories and light fittings | C29: Removal of existing electrical points, accessories and light fittings. | D29: lot | E29: 1 | F29: 1290 | G29: =IF(AND(ISNUMBER(E29),ISNUMBER(F29)),ROUND(E29*F29,2),"") -> 1290
A30: 02.12 | B30: Removal of existing exposed plumbing | C30: Removal of existing exposed plumbing pipework. | D30: lot | E30: 1 | F30: 970 | G30: =IF(AND(ISNUMBER(E30),ISNUMBER(F30)),ROUND(E30*F30,2),"") -> 970
... A38: 02.20 | B38: Removal of existing entrance stairs | C38: Removal of the existing entrance stairs, including cutting, loading and removal of waste, ahead of the new floating steps. | D38: lot | E38: 1 | F38: 970 | G38: =IF(AND(ISNUMBER(E38),ISNUMBER(F38)),ROUND(E38*F38,2),"") -> 970
A39: 02.21 | B39: Removal of lawn and garden planting | C39: Removal of existing lawn, shrubs and garden planting in the development areas, including roots, loading and removal to a licensed site. | D39: m² | E39: 65 | F39: 11.5 | G39: =IF(AND(ISNUMBER(E39),ISNUMBER(F39)),ROUND(E39*F39,2),"") -> 747.5 | H39: Provisional quantity – remeasured
A40: Total – Chapter 2 | G40: =IF(COUNT(G19:G39)=0,"",SUM(G19:G39)) -> 38872.5
A42: Chapter 3 — Structural Works and Extensions
A43: 03.01 | B43: Enlargement of living-room balcony and new pergola | C43: Complete structural works per the structural engineer's drawings and specification. | D43: lot | E43: 1 | F43: 22600 | G43: =IF(AND(ISNUMBER(E43),ISNUMBER(F43)),ROUND(E43*F43,2),"") -> 22600 | H43: Lump sum – adjusted on receipt of structural drawings
A44: 03.02 | B44: New room addition on the gallery level | C44: Complete structural works for the room per structural and architectural drawings, including connections to the existing structure and openings. Finishes and services under their own chapters. | D44: lot | E44: 1 | F44: 38700 | G44: =IF(AND(ISNUMBER(E44),ISNUMBER(F44)),ROUND(E44*F44,2),"") -> 38700 | H44: Lump sum – adjusted on receipt of structural drawings
A45: 03.03 | B45: New entrance and staircase | C45: Complete works for the new entrance and staircase per the structural engineer. | D45: lot | E45: 1 | F45: 12300 | G45: =IF(AND(ISNUMBER(E45),ISNUMBER(F45)),ROUND(E45*F45,2),"") -> 12300 | H45: Lump sum – adjusted on receipt of structural drawings
A46: 03.04 | B46: Strengthening of existing internal staircase | C46: Strengthening per the structural engineer, after removal of the balustrade. | D46: lot | E46: 1 | F46: 5800 | G46: =IF(AND(ISNUMBER(E46),ISNUMBER(F46)),ROUND(E46*F46,2),"") -> 5800 | H46: Lump sum – adjusted on receipt of structural drawings
A47: 03.05 | B47: Floating entrance stairs | C47: 12 new floating (cantilevered) steps at the entrance replacing the existing stairs, approx. 1.15 m wide, including reinforcement, anchoring and preparation for cladding, per structural and architectural drawings. Cladding under item 13.08. | D47: pcs | E47: 12 | F47: 900 | G47: =IF(AND(ISNUMBER(E47),ISNUMBER(F47)),ROUND(E47*F47,2),"") -> 10800 | H47: Lump sum – adjusted on receipt of structural drawings; Final dimension per existing on site
A48: Total – Chapter 3 | G48: =IF(COUNT(G43:G47)=0,"",SUM(G43:G47)) -> 90200
A50: Chapter 4 — New Block Wall Partitions
A51: 04.01 | B51: New block walls (20 cm) – basement | C51: Block walls per drawings. | D51: m² | E51: 6.3 | F51: 97 | G51: =IF(AND(ISNUMBER(E51),ISNUMBER(F51)),ROUND(E51*F51,2),"") -> 611.1
A52: 04.02 | B52: New block walls (20 cm) – ground floor | C52: Block walls per drawings. | D52: m² | E52: 17.7 | F52: 97 | G52: =IF(AND(ISNUMBER(E52),ISNUMBER(F52)),ROUND(E52*F52,2),"") -> 1716.9
A53: 04.03 | B53: New block walls (20 cm) – first floor and gallery | C53: Block walls per drawings. | D53: m² | E53: 2.08 | F53: 97 | G53: =IF(AND(ISNUMBER(E53),ISNUMBER(F53)),ROUND(E53*F53,2),"") -> 201.76
A54: Total – Chapter 4 | G54: =IF(COUNT(G51:G53)=0,"",SUM(G51:G53)) -> 2529.76
A56: Chapter 5 — Plumbing, Sanitary Fixtures and Taps
A57: 05.01 | B57: Wall-hung WC pan | C57: Installation, fixing to the support frame, connection to flush system and drainage, and testing. | D57: pcs | E57: 7 | F57: 258 | G57: =IF(AND(ISNUMBER(E57),ISNUMBER(F57)),ROUND(E57*F57,2),"") -> 1806 | H57: Installation only; supply by the Employer
A58: 05.02 | B58: Concealed cistern and support frame | C58: Installation, anchoring, connection to water and WC, and leak test before closing the cladding. | D58: pcs | E58: 7 | F58: 355 | G58: =IF(AND(ISNUMBER(E58),ISNUMBER(F58)),ROUND(E58*F58,2),"") -> 2485 | H58: Installation only; supply by the Employer
A59: 05.03 | B59: Flush plate | C59: Installation matching the concealed cistern and testing. | D59: pcs | E59: 7 | F59: 48.5 | G59: =IF(AND(ISNUMBER(E59),ISNUMBER(F59)),ROUND(E59*F59,2),"") -> 339.5 | H59: Installation only; supply by the Employer
A60: 05.04 | B60: Hydraulic soft-close WC seat | C60: Installation and adjustment. | D60: pcs | E60: 7 | F60: 48.5 | G60: =IF(AND(ISNUMBER(E60),ISNUMBER(F60)),ROUND(E60*F60,2),"") -> 339.5 | H60: Installation only; supply by the Employer
A61: 05.05 | B61: Freestanding washbasin | C61: Installation, fixing, connection to drainage and sealing. | D61: pcs | E61: 1 | F61: 194 | G61: =IF(AND(ISNUMBER(E61),ISNUMBER(F61)),ROUND(E61*F61,2),"") -> 194 | H61: Installation only; supply by the Employer
A62: 05.06 | B62: Wall-mounted tap | C62: Installation and connection. | D62: pcs | E62: 6 | F62: 97 | G62: =IF(AND(ISNUMBER(E62),ISNUMBER(F62)),ROUND(E62*F62,2),"") -> 582 | H62: Installation only; supply by the Employer
A63: 05.07 | B63: Rain shower head | C63: Installation and connection. | D63: pcs | E63: 6 | F63: 145 | G63: =IF(AND(ISNUMBER(E63),ISNUMBER(F63)),ROUND(E63*F63,2),"") -> 870 | H63: Installation only; supply by the Employer
A64: 05.08 | B64: Three-way diverter valve | C64: Installation of three-way diverter (Interpoz-type) valve and trim. | D64: pcs | E64: 10 | F64: 145 | G64: =IF(AND(ISNUMBER(E64),ISNUMBER(F64)),ROUND(E64*F64,2),"") -> 1450 | H64: Installation only; supply by the Employer
A65: 05.09 | B65: Four-way diverter valve | C65: Installation of four-way diverter (Interpoz-type) valve and trim. | D65: pcs | E65: 2 | F65: 194 | G65: =IF(AND(ISNUMBER(E65),ISNUMBER(F65)),ROUND(E65*F65,2),"") -> 388 | H65: Installation only; supply by the Employer
A66: 05.10 | B66: Shower hand-set holder | C66: Installation of hand-shower holder. | D66: pcs | E66: 7 | F66: 81 | G66: =IF(AND(ISNUMBER(E66),ISNUMBER(F66)),ROUND(E66*F66,2),"") -> 567 | H66: Installation only; supply by the Employer
A67: 05.11 | B67: 10/10 linear drain channel (showers) | C67: Installation and connection of drain channel. | D67: pcs | E67: 5 | F67: 210 | G67: =IF(AND(ISNUMBER(E67),ISNUMBER(F67)),ROUND(E67*F67,2),"") -> 1050 | H67: Installation only; supply by the Employer
A68: 05.12 | B68: 110 overflow channel for bathtub | C68: Installation of overflow channel. | D68: pcs | E68: 1 | F68: 484 | G68: =IF(AND(ISNUMBER(E68),ISNUMBER(F68)),ROUND(E68*F68,2),"") -> 484 | H68: Installation only; supply by the Employer
... A70: 05.15 | B70: Bath filler tap | C70: Installation of bath filler tap. | D70: pcs | E70: 1 | F70: 323 | G70: =IF(AND(ISNUMBER(E70),ISNUMBER(F70)),ROUND(E70*F70,2),"") -> 323 | H70: Installation only; supply by the Employer
A71: 05.16 | B71: Kitchen sink | C71: Installed by the countertop supplier. | D71: pcs | E71: 3 | F71: By countertop supplier | G71: =IF(AND(ISNUMBER(E71),ISNUMBER(F71)),ROUND(E71*F71,2),"")
A72: 05.17 | B72: Kitchen pull-out tap | C72: Installation, connection and function test. | D72: pcs | E72: 5 | F72: 145 | G72: =IF(AND(ISNUMBER(E72),ISNUMBER(F72)),ROUND(E72*F72,2),"") -> 725 | H72: Installation only; supply by the Employer
A73: 05.18 | B73: Outdoor kitchen sink | C73: Installed by the countertop supplier. | D73: pcs | E73: 2 | F73: By countertop supplier | G73: =IF(AND(ISNUMBER(E73),ISNUMBER(F73)),ROUND(E73*F73,2),"")
A74: 05.19 | B74: Outdoor pull-out tap | C74: Installation and connection. | D74: pcs | E74: 2 | F74: 145 | G74: =IF(AND(ISNUMBER(E74),ISNUMBER(F74)),ROUND(E74*F74,2),"") -> 290 | H74: Installation only; supply by the Employer
A75: 05.20 | B75: Countertop basin / trough – guest WC | C75: Installation and connection. | D75: pcs | E75: 1 | F75: 210 | G75: =IF(AND(ISNUMBER(E75),ISNUMBER(F75)),ROUND(E75*F75,2),"") -> 210 | H75: Installation only; supply by the Employer
A76: 05.21 | B76: Nile tap | C76: Installation of tap. | D76: pcs | E76: 11 | F76: 58 | G76: =IF(AND(ISNUMBER(E76),ISNUMBER(F76)),ROUND(E76*F76,2),"") -> 638 | H76: Installation only; supply by the Employer
A77: 05.22 | B77: Tap with vanity unit – assembly | C77: Installation of tap and vanity unit as an assembly. | D77: pcs | E77: 1 | F77: 580 | G77: =IF(AND(ISNUMBER(E77),ISNUMBER(F77)),ROUND(E77*F77,2),"") -> 580 | H77: Installation only; supply by the Employer
A78: 05.23 | B78: 60 external overflow channel | C78: Installation of external overflow channel. | D78: pcs | E78: 1 | F78: 387 | G78: =IF(AND(ISNUMBER(E78),ISNUMBER(F78)),ROUND(E78*F78,2),"") -> 387 | H78: Installation only; supply by the Employer
A79: 05.24 | B79: Bar sink | C79: Installation and connection. | D79: pcs | E79: 2 | F79: 177 | G79: =IF(AND(ISNUMBER(E79),ISNUMBER(F79)),ROUND(E79*F79,2),"") -> 354 | H79: Installation only; supply by the Employer
A80: 05.25 | B80: Hot and cold water point | C80: Supply pipework and point. | D80: pt | E80: 23 | F80: 387 | G80: =IF(AND(ISNUMBER(E80),ISNUMBER(F80)),ROUND(E80*F80,2),"") -> 8901
A81: 05.26 | B81: Cold water point for cistern | C81: Supply pipework and point. | D81: pt | E81: 7 | F81: 161 | G81: =IF(AND(ISNUMBER(E81),ISNUMBER(F81)),ROUND(E81*F81,2),"") -> 1127
A82: 05.27 | B82: Sewage point for WC | C82: Drainage pipework and point. | D82: pt | E82: 7 | F82: 226 | G82: =IF(AND(ISNUMBER(E82),ISNUMBER(F82)),ROUND(E82*F82,2),"") -> 1582
A83: 05.28 | B83: Drain point for basin and bathtub | C83: Drainage pipework and point. | D83: pt | E83: 15 | F83: 145 | G83: =IF(AND(ISNUMBER(E83),ISNUMBER(F83)),ROUND(E83*F83,2),"") -> 2175
A84: 05.29 | B84: Water and drain point for washing machine | C84: Supply and drain points. | D84: pt | E84: 2 | F84: 290 | G84: =IF(AND(ISNUMBER(E84),ISNUMBER(F84)),ROUND(E84*F84,2),"") -> 580
A85: 05.30 | B85: Utility (bucket) tap | C85: Installation of utility tap. | D85: pcs | E85: 2 | F85: 58 | G85: =IF(AND(ISNUMBER(E85),ISNUMBER(F85)),ROUND(E85*F85,2),"") -> 116
A86: 05.32 | B86: Main supply lines and floor manifolds | C86: Main water supply lines and floor-level manifolds. | D86: lot | E86: 1 | F86: 6500 | G86: =IF(AND(ISNUMBER(E86),ISNUMBER(F86)),ROUND(E86*F86,2),"") -> 6500
A87: 05.33 | B87: Main sewage and drainage system | C87: Main sewage and drainage system. | D87: lot | E87: 1 | F87: 5800 | G87: =IF(AND(ISNUMBER(E87),ISNUMBER(F87)),ROUND(E87*F87,2),"") -> 5800
A88: 05.34 | B88: Water heater – installation and connection | C88: Installation and connection of water heater. | D88: pcs | E88: 1 | F88: 387 | G88: =IF(AND(ISNUMBER(E88),ISNUMBER(F88)),ROUND(E88*F88,2),"") -> 387 | H88: Installation only; supply by the Employer
A89: 05.35 | B89: Pressure and leak tests, as-built drawings | C89: Testing of the plumbing systems and as-built documentation. | D89: lot | E89: 1 | F89: 810 | G89: =IF(AND(ISNUMBER(E89),ISNUMBER(F89)),ROUND(E89*F89,2),"") -> 810
A90: Total – Chapter 5 | G90: =IF(COUNT(G57:G89)=0,"",SUM(G57:G89)) -> 42750
A92: Chapter 6 — Electrical Works
A93: 06.01 | B93: Standard socket point | C93: Wiring to the relevant circuit, accessory and test. | D93: pcs | E93: 119 | F93: 141 | G93: =IF(AND(ISNUMBER(E93),ISNUMBER(F93)),ROUND(E93*F93,2),"") -> 16779
A94: 06.02 | B94: Waterproof socket point | C94: Waterproof socket point (IP44 or above). | D94: pcs | E94: 51 | F94: 167 | G94: =IF(AND(ISNUMBER(E94),ISNUMBER(F94)),ROUND(E94*F94,2),"") -> 8517
A95: 06.03 | B95: Infrastructure for electric roller shutter | C95: Conduit and wiring for electric shutter operation. | D95: pcs | E95: 18 | F95: 198 | G95: =IF(AND(ISNUMBER(E95),ISNUMBER(F95)),ROUND(E95*F95,2),"") -> 3564
A96: 06.05 | B96: Three-phase socket point | C96: Three-phase socket point. | D96: pcs | E96: 1 | F96: 470 | G96: =IF(AND(ISNUMBER(E96),ISNUMBER(F96)),ROUND(E96*F96,2),"") -> 470
A97: 06.06 | B97: Extension of main distribution board | C97: Extension of the main board for the total added load. | D97: lot | E97: 1 | F97: 2740 | G97: =IF(AND(ISNUMBER(E97),ISNUMBER(F97)),ROUND(E97*F97,2),"") -> 2740
A98: 06.07 | B98: Electricity company pillar – supply and installation | C98: Supply and installation of the new electricity company pillar at the plot entrance. | D98: lot | E98: 1 | F98: 2260 | G98: =IF(AND(ISNUMBER(E98),ISNUMBER(F98)),ROUND(E98*F98,2),"") -> 2260
A99: 06.09 | B99: Final electrical inspection | C99: Final inspection by a certified inspector, certificate and test report. | D99: lot | E99: 1 | F99: 810 | G99: =IF(AND(ISNUMBER(E99),ISNUMBER(F99)),ROUND(E99*F99,2),"") -> 810
A100: 06.10 | B100: Power socket point | C100: Power socket point. | D100: pcs | E100: 9 | F100: 198 | G100: =IF(AND(ISNUMBER(E100),ISNUMBER(F100)),ROUND(E100*F100,2),"") -> 1782
A101: 06.11 | B101: Supply point for A/C unit | C101: Dedicated supply point for an A/C unit. | D101: pt | E101: 8 | F101: 391 | G101: =IF(AND(ISNUMBER(E101),ISNUMBER(F101)),ROUND(E101*F101,2),"") -> 3128
A102: 06.12 | B102: Direct connection to the board – hob, oven and dedicated appliances | C102: Direct connection to the distribution board on a dedicated line with separate protection for each appliance (hob, oven, dishwasher, dryer and other dedicated loads), including cable, conduit, final connection and testing. | D102: lot | E102: 1 | F102: 1830 | G102: =IF(AND(ISNUMBER(E102),ISNUMBER(F102)),ROUND(E102*F102,2),"") -> 1830
A103: 06.13 | B103: Boiler switch with indicator light | C103: Boiler switch with indicator light. | D103: pcs | E103: 1 | F103: 183 | G103: =IF(AND(ISNUMBER(E103),ISNUMBER(F103)),ROUND(E103*F103,2),"") -> 183
A104: Total – Chapter 6 | G104: =IF(COUNT(G93:G103)=0,"",SUM(G93:G103)) -> 42063
A106: Chapter 7 — Lighting and Light Switches
A107: 07.01 | B107: Lighting switches (single) | C107: Installation of lighting switches. | D107: pcs | E107: 62 | F107: 78 | G107: =IF(AND(ISNUMBER(E107),ISNUMBER(F107)),ROUND(E107*F107,2),"") -> 4836
A108: 07.02 | B108: Two-way switches | C108: Installation of two-way switches. | D108: pcs | E108: 16 | F108: 104 | G108: =IF(AND(ISNUMBER(E108),ISNUMBER(F108)),ROUND(E108*F108,2),"") -> 1664
A109: 07.02a | B109: Intermediate (cross) switch | C109: Installation of an intermediate (cross) switch on a lighting circuit controlled from three or more places, between the two-way switches, including finish accessory, intermediate wiring and testing. | D109: pcs | E109: 3 | F109: 125 | G109: =IF(AND(ISNUMBER(E109),ISNUMBER(F109)),ROUND(E109*F109,2),"") -> 375
A110: 07.03 | B110: Ceiling-mounted light fitting | C110: Installation, electrical connection and test. | D110: pcs | E110: 15 | F110: 115 | G110: =IF(AND(ISNUMBER(E110),ISNUMBER(F110)),ROUND(E110*F110,2),"") -> 1725 | H110: Installation only; supply by the Employer
A111: 07.04 | B111: Pendant light fitting | C111: Installation, suspension system, height adjustment per plan, connection and test. | D111: pcs | E111: 22 | F111: 167 | G111: =IF(AND(ISNUMBER(E111),ISNUMBER(F111)),ROUND(E111*F111,2),"") -> 3674 | H111: Installation only; supply by the Employer
A112: 07.05 | B112: Protected wall light fitting | C112: Installation and connection. | D112: pcs | E112: 30 | F112: 115 | G112: =IF(AND(ISNUMBER(E112),ISNUMBER(F112)),ROUND(E112*F112,2),"") -> 3450 | H112: Installation only; supply by the Employer
A113: 07.06 | B113: Protected recessed wall light fitting | C113: Installation and connection. | D113: pcs | E113: 35 | F113: 157 | G113: =IF(AND(ISNUMBER(E113),ISNUMBER(F113)),ROUND(E113*F113,2),"") -> 5495 | H113: Installation only; supply by the Employer
A114: 07.07 | B114: Recessed spot in gypsum ceiling | C114: Installation and connection. | D114: pcs | E114: 25 | F114: 44.5 | G114: =IF(AND(ISNUMBER(E114),ISNUMBER(F114)),ROUND(E114*F114,2),"") -> 1112.5 | H114: Installation only; supply by the Employer
A115: 07.08 | B115: Concealed LED strip | C115: Installation of concealed LED strip. | D115: pcs | E115: 11 | F115: 183 | G115: =IF(AND(ISNUMBER(E115),ISNUMBER(F115)),ROUND(E115*F115,2),"") -> 2013 | H115: Installation only; supply by the Employer
...

Sheet Summary
A1: Summary of Quotation
A3: Chapter | B3: Amount | C3: % of total
A4: 1. Preparation and Site Establishment | B4: ='Quotation'!G16 -> 22816.5 | C4: =IF($B$17=0,0,B4/$B$17) -> 0.051692172
A5: 2. Demolition, Removals and Disposal | B5: ='Quotation'!G40 -> 38872.5 | C5: =IF($B$17=0,0,B5/$B$17) -> 0.08806802
A6: 3. Structural Works and Extensions | B6: ='Quotation'!G48 -> 90200 | C6: =IF($B$17=0,0,B6/$B$17) -> 0.2043536
A7: 4. New Block Wall Partitions | B7: ='Quotation'!G54 -> 2529.76 | C7: =IF($B$17=0,0,B7/$B$17) -> 0.0057313256
A8: 5. Plumbing, Sanitary Fixtures and Taps | B8: ='Quotation'!G90 -> 42750 | C8: =IF($B$17=0,0,B8/$B$17) -> 0.096852733
A9: 6. Electrical Works | B9: ='Quotation'!G104 -> 42063 | C9: =IF($B$17=0,0,B9/$B$17) -> 0.095296292
A10: 7. Lighting and Light Switches | B10: ='Quotation'!G126 -> 45055.5 | C10: =IF($B$17=0,0,B10/$B$17) -> 0.10207598
A11: 9. Gypsum Partitions and Ceilings | B11: ='Quotation'!G133 -> 10676.1 | C11: =IF($B$17=0,0,B11/$B$17) -> 0.024187356
A12: 10. Internal Waterproofing | B12: ='Quotation'!G139 -> 10306.5 | C12: =IF($B$17=0,0,B12/$B$17) -> 0.023350004
A13: 12. Window Sills and Sealing | B13: ='Quotation'!G145 -> 7154.42 | C13: =IF($B$17=0,0,B13/$B$17) -> 0.016208775
A14: 13. Flooring, Wall Tiling and Cladding | B14: ='Quotation'!G155 -> 66017.5 | C14: =IF($B$17=0,0,B14/$B$17) -> 0.14956667
A15: 14. Plaster, Skim Coat and Paint | B15: ='Quotation'!G161 -> 41220 | C15: =IF($B$17=0,0,B15/$B$17) -> 0.093386424
A16: 17. External Development | B16: ='Quotation'!G169 -> 21730 | C16: =IF($B$17=0,0,B16/$B$17) -> 0.04923064
A17: Total before VAT | B17: =SUM(B4:B16) -> 441391.78
A18: VAT (20%) | B18: ='Quotation'!G172 -> 88278.36
A19: TOTAL INCLUDING VAT | B19: =B17+B18 -> 529670.14

Sheet Terms & Exclusions
A1: # | B1: Terms & Exclusions
A2: 1 | B2: Basis | C2: The quotation is based on the Technical Specification Book (rev. 20, 06/07/2026), the architectural drawings "New Construction" – ground and first floor (17/09/2026) and the Contractor Quantity Schedule dated 24/09/2026. Where documents differ, the schedule of 24/09/2026 was used.
A3: 2 | B3: Quantities | C3: Quantities per the above documents. Items marked "provisional" or "per measurement on site" will be remeasured; the final account follows quantities actually executed.
A4: 3 | B4: Structure | C4: Chapter 3 (balcony and pergola, gallery room, entrance and stairs, strengthening of internal stairs) is a lump sum per the structural engineer's drawings; the price will be adjusted on receipt of the complete structural drawings.
A5: 4 | B5: Supply | C5: Sanitary ware and taps, light fittings, air-conditioning units, water heaters and floor and wall tiles are supplied by the Employer; the Contractor installs. Kitchen sinks are installed by the countertop supplier.
A6: 5 | B6: Exclusions | C6: Swimming pool; carpentry (kitchen, bathroom and wardrobe cabinets); aluminium windows and doors, interior and entrance doors, gates and shutters; parapet works; furniture; permits and fees; consultants' fees (structural, waterproofing, lighting); electricity company charges for the supply upgrade.
A7: 6 | B7: Tests | C7: Required tests and approvals (structural engineer, waterproofing consultant, certified electrical inspector, flood and pressure tests) are included.
A8: 7 | B8: Prices | C8: Prices in GBP, excluding VAT, price base October 2026, no indexation unless agreed otherwise.
A9: 8 | B9: Commercial terms | C9: Validity: [__ days] | Payment terms: [__] | Programme: [__]

Sheet Market survey (internal)
A1: Category | B1: Market data found (2026) | C1: Sources
A2: Plasterboard stud partition | B2: £30–£65/m²; acoustic / insulated £55–£100/m² | C2: trade2base.com/blog/stud-wall-costs-uk ; trade2base.com/blog/dry-lining-costs-uk ; fantasticservices.com/cost-guides/handyman/plastering/
A3: Large-format porcelain floor tiling (labour) | B3: £50–£80/m² (labour only); London/South East +20–30% | C3: trade2base.com/blog/tiling-pricing-guide-uk ; myjobquote.co.uk/questions/large-format-tile-installation-cost
A4: New socket point (electrician) | B4: £100–£250 per socket (new location) | C4: fantasticservices.com/cost-guides/electrical/socket-replacement/ ; myjobquote.co.uk/costs/new-plug-sockets
A5: Interior painting | B5: £14–£26/m² (prep, 2 coats, materials); skim coat adds £12–£20/m² | C5: bestbuilders.co.uk/costs/painting-cost-calculator ; trade2base.com/blog/painting-decorating-costs-uk
A6: Concrete path | B6: £60–£90/m² supplied and laid (2026) | C6: trade2base.com/blog/garden-path-costs-uk ; less.co.uk/home-improvements/driveways/concrete-cost
A7: Scaffolding | B7: ≈ £22.5/m² (one listing); typical house £1,500–£3,500 erected, hired, dismantled | C7: checkatrade.com (GU6 listing) ; lakeside-hire.co.uk ; less.co.uk/home-improvements/scaffolding/cost
A8: Exchange rate | B8: ≈ 4.10 ILS per GBP (9 Sep 2026 snapshot 4.0953; October values are forecasts only) | C8: longforecast.com/gbp-ils ; ofx.com
A10: Method: each unit rate = Israeli renovation-level base rate (ILS) × category multiplier ÷ exchange rate, then + 15% overheads and profit. Multipliers were calibrated on the anchors below (partition, tiling, electrical points, painting, concrete path, scaffolding); trades without an anchor use the average multiplier of the anchored ones. Calibration multipliers: part=0.62, tile=0.95, elec=1.86, paint=1.6, conc=0.77, scaf=1.69, gen=1.15. FX 4.1 ILS/GBP.
A11: Caveats: sources are mostly trade/lead-generation websites with wide, partly undated ranges; no official price book was used. The site is in Haifa, Israel – rates are UK market reference rates and were not adjusted for Israeli site conditions or logistics. English version assumes the UK market (GBP); confirm if another English-speaking market (e.g. USA/USD) is intended. All prices should be verified against supplier quotations before submission.
