Workbook

Sheet Quotation
A1: QUOTATION – Renovation and Extension, 53 Shlonsky St., Haifa
A2: Employer: Zohar Mor Yosef and Rami Dana | Contractor: [Contractor name] | Date: 08/10/2026 | Quotation no.: [__]
A3: All amounts in NIS (₪), excluding VAT, price base October 2026. Rates include contractor's overheads and profit.
A5: Item | B5: Description | C5: Scope | D5: Unit | E5: Qty | F5: Qty basis | G5: Rate (₪) | H5: Amount (₪) | I5: Remarks
A6: Chapter 1 — Preparation and Site Establishment
A7: 01.01 | B7: Site establishment | C7: Setting up work and storage areas, workers' facilities and access coordination. | D7: lot | E7: 1 | F7: Per documents | G7: 9200 | H7: =ROUND(E7*G7,2)
A8: 01.02 | B8: Site hoarding, signage and safety | C8: Temporary hoarding, site and hazard signage, and the safety measures required for the works. | D8: lot | E8: 1 | F8: Per documents | G8: 4600 | H8: =ROUND(E8*G8,2)
A9: 01.03 | B9: Temporary water connection | C9: Temporary water connection from the approved source, tested. | D9: lot | E9: 1 | F9: Per documents | G9: 1725 | H9: =ROUND(E9*G9,2)
A10: 01.04 | B10: Temporary electrical connection | C10: Temporary power connection by a licensed electrician, with protection and testing. | D10: lot | E10: 1 | F10: Per documents | G10: 3450 | H10: =ROUND(E10*G10,2)
A11: 01.05 | B11: Protection of existing elements | C11: Protective covers for floors, openings, windows, stairs, railings, walls and plants to be retained. | D11: lot | E11: 1 | F11: Per documents | G11: 5750 | H11: =ROUND(E11*G11,2)
A12: 01.06 | B12: Survey, verification and laser setting-out | C12: Survey of the existing building, verification against architectural and services drawings, setting-out of positions and levels. | D12: lot | E12: 1 | F12: Per documents | G12: 3450 | H12: =ROUND(E12*G12,2)
A13: 01.07 | B13: Waste skip and waste collection area | C13: Skip placement and a waste collection area; removal of waste to a licensed site. | D13: lot | E13: 1 | F13: Per documents | G13: 10350 | H13: =ROUND(E13*G13,2)
A14: 01.08 | B14: Ongoing site cleaning | C14: Periodic cleaning of work areas and passages throughout the works. | D14: lot | E14: 1 | F14: Per documents | G14: 10350 | H14: =ROUND(E14*G14,2)
A15: 01.09 | B15: External scaffolding | C15: Erection, rental for the works period, maintenance and removal of compliant external scaffolding around the facades, for sawing the decorative concrete frames, parapet works and facade plaster. | D15: m² | E15: 225 | F15: Provisional – remeasure | G15: 98 | H15: =ROUND(E15*G15,2)
A16: Total – Chapter 01 | H16: =SUM(H7:H15)
A18: Chapter 2 — Demolition, Removals and Disposal
A19: 02.01 | B19: Demolition of walls and partitions – basement | C19: Demolition of existing walls and partitions per demolition drawings. | D19: m² | E19: 62 | F19: Per documents | G19: 138 | H19: =ROUND(E19*G19,2)
A20: 02.02 | B20: Demolition of walls and partitions – ground floor | C20: Demolition of existing walls and partitions per demolition drawings. | D20: m² | E20: 51 | F20: Per documents | G20: 138 | H20: =ROUND(E20*G20,2)
A21: 02.03 | B21: Demolition of walls and partitions – first floor | C21: Demolition of existing walls and partitions per demolition drawings. | D21: m² | E21: 85 | F21: Per documents | G21: 138 | H21: =ROUND(E21*G21,2)
A22: 02.04 | B22: Removal of existing gypsum ceilings | C22: Removal of existing suspended gypsum ceilings. | D22: m² | E22: 10 | F22: Per documents | G22: 57 | H22: =ROUND(E22*G22,2)
A23: 02.05 | B23: Removal of existing flooring | C23: Removal of existing floor finishes. | D23: m² | E23: 40 | F23: Per documents | G23: 103 | H23: =ROUND(E23*G23,2)
A24: 02.06 | B24: Removal of existing kitchen cabinets | C24: Removal of existing kitchen cabinets, complete. | D24: lot | E24: 1 | F24: Per documents | G24: 2300 | H24: =ROUND(E24*G24,2)
A25: 02.07 | B25: Removal of other existing joinery | C25: Removal of other existing cabinets and joinery. | D25: pcs | E25: 1 | F25: Per documents | G25: 2875 | H25: =ROUND(E25*G25,2)
A26: 02.08 | B26: Removal of existing aluminium windows and shutters | C26: Complete removal of existing aluminium windows and roller shutters. | D26: lot | E26: 1 | F26: Per documents | G26: 6900 | H26: =ROUND(E26*G26,2)
A27: 02.09 | B27: Removal of interior and entrance doors and frames | C27: Complete removal of interior and entrance doors and frames. | D27: lot | E27: 1 | F27: Per documents | G27: 4025 | H27: =ROUND(E27*G27,2)
A28: 02.10 | B28: Removal of bathrooms, WCs and sanitary ware | C28: Complete removal of existing bathrooms, WCs and sanitary fixtures. | D28: lot | E28: 1 | F28: Per documents | G28: 9200 | H28: =ROUND(E28*G28,2)
A29: 02.11 | B29: Removal of electrical points, accessories and light fittings | C29: Removal of existing electrical points, accessories and light fittings. | D29: lot | E29: 1 | F29: Per documents | G29: 4600 | H29: =ROUND(E29*G29,2)
A30: 02.12 | B30: Removal of existing exposed plumbing | C30: Removal of existing exposed plumbing pipework. | D30: lot | E30: 1 | F30: Per documents | G30: 3450 | H30: =ROUND(E30*G30,2)
... A38: 02.20 | B38: Removal of granolithic flooring | C38: Removal of granolithic flooring in the parking area, entrance and paths. | D38: m² | E38: 100 | F38: Per documents | G38: 115 | H38: =ROUND(E38*G38,2)
A39: Total – Chapter 02 | H39: =SUM(H19:H38)
A41: Chapter 3 — Structural Works and Extensions
A42: 03.01 | B42: Enlargement of living-room balcony and new pergola | C42: Complete structural works per the structural engineer's drawings and specification. | D42: lot | E42: 1 | F42: Estimate – per engineer | G42: 80500 | H42: =ROUND(E42*G42,2) | I42: Provisional sum pending structural drawings
A43: 03.02 | B43: New room addition on the gallery level | C43: Complete structural works for the room addition per structural and architectural drawings, including connections to the existing structure and openings. Finishes and services under their own chapters. | D43: lot | E43: 1 | F43: Estimate – per engineer | G43: 138000 | H43: =ROUND(E43*G43,2) | I43: Provisional sum pending structural drawings
A44: 03.03 | B44: New entrance and staircase | C44: Complete works for the new entrance and staircase per the structural engineer. | D44: lot | E44: 1 | F44: Estimate – per engineer | G44: 43700 | H44: =ROUND(E44*G44,2) | I44: Provisional sum pending structural drawings
A45: 03.04 | B45: Strengthening of existing internal staircase | C45: Strengthening per the structural engineer, after removal of the balustrade. | D45: lot | E45: 1 | F45: Estimate – per engineer | G45: 20700 | H45: =ROUND(E45*G45,2) | I45: Provisional sum pending structural drawings
A46: Total – Chapter 03 | H46: =SUM(H42:H45)
A48: Chapter 4 — New Block Wall Partitions
A49: 04.01 | B49: New block walls (20 cm) – basement | C49: Block walls per drawings. | D49: m² | E49: 6.3 | F49: Per documents | G49: 345 | H49: =ROUND(E49*G49,2)
A50: 04.02 | B50: New block walls (20 cm) – ground floor | C50: Block walls per drawings. | D50: m² | E50: 17.7 | F50: Per documents | G50: 345 | H50: =ROUND(E50*G50,2)
A51: 04.03 | B51: New block walls (20 cm) – first floor and gallery | C51: Block walls per drawings. | D51: m² | E51: 2.08 | F51: Per documents | G51: 345 | H51: =ROUND(E51*G51,2)
A52: Total – Chapter 04 | H52: =SUM(H49:H51)
A54: Chapter 5 — Plumbing, Sanitary Fixtures and Taps
A55: 05.01 | B55: Wall-hung WC pan | C55: Installation, fixing to the support frame, connection to flush system and drainage, and testing. | D55: pcs | E55: 7 | F55: Per documents | G55: 920 | H55: =ROUND(E55*G55,2) | I55: Installation only; supply by Employer
A56: 05.02 | B56: Concealed cistern and support frame | C56: Installation, anchoring, connection to water and WC, and leak test before closing the cladding. | D56: pcs | E56: 7 | F56: Per documents | G56: 1265 | H56: =ROUND(E56*G56,2) | I56: Installation only; supply by Employer
A57: 05.03 | B57: Flush plate | C57: Installation matching the concealed cistern and testing. | D57: pcs | E57: 7 | F57: Per documents | G57: 172 | H57: =ROUND(E57*G57,2) | I57: Installation only; supply by Employer
A58: 05.04 | B58: Hydraulic soft-close WC seat | C58: Installation and adjustment. | D58: pcs | E58: 7 | F58: Per documents | G58: 172 | H58: =ROUND(E58*G58,2) | I58: Installation only; supply by Employer
A59: 05.05 | B59: Freestanding washbasin | C59: Installation, fixing, connection to drainage and sealing. | D59: pcs | E59: 1 | F59: Per documents | G59: 690 | H59: =ROUND(E59*G59,2) | I59: Installation only; supply by Employer
A60: 05.06 | B60: Wall-mounted tap | C60: Installation and connection. | D60: pcs | E60: 6 | F60: Per documents | G60: 345 | H60: =ROUND(E60*G60,2) | I60: Installation only; supply by Employer
A61: 05.07 | B61: Rain shower head | C61: Installation and connection. | D61: pcs | E61: 6 | F61: Per documents | G61: 518 | H61: =ROUND(E61*G61,2) | I61: Installation only; supply by Employer
A62: 05.08 | B62: Three-way diverter valve | C62: Installation of three-way diverter (Interpoz-type) valve and trim. | D62: pcs | E62: 10 | F62: Per documents | G62: 518 | H62: =ROUND(E62*G62,2) | I62: Installation only; supply by Employer
A63: 05.09 | B63: Four-way diverter valve | C63: Installation of four-way diverter (Interpoz-type) valve and trim. | D63: pcs | E63: 2 | F63: Per documents | G63: 690 | H63: =ROUND(E63*G63,2) | I63: Installation only; supply by Employer
A64: 05.10 | B64: Shower hand-set holder | C64: Installation of hand-shower holder. | D64: pcs | E64: 7 | F64: Per documents | G64: 288 | H64: =ROUND(E64*G64,2) | I64: Installation only; supply by Employer
A65: 05.11 | B65: 10/10 linear drain channel | C65: Installation and connection of drain channel. | D65: pcs | E65: 5 | F65: Per documents | G65: 747 | H65: =ROUND(E65*G65,2) | I65: Installation only; supply by Employer
A66: 05.12 | B66: 110 overflow channel | C66: Installation of overflow channel. | D66: pcs | E66: 1 | F66: Per documents | G66: 1725 | H66: =ROUND(E66*G66,2) | I66: Installation only; supply by Employer
... A77: 05.24 | B77: Bar sink | C77: Installation and connection. | D77: pcs | E77: 2 | F77: Per documents | G77: 632 | H77: =ROUND(E77*G77,2) | I77: Installation only; supply by Employer
A78: 05.25 | B78: Hot and cold water point | C78: Supply pipework and point. | D78: pt | E78: 23 | F78: Per documents | G78: 1380 | H78: =ROUND(E78*G78,2)
A79: 05.26 | B79: Cold water point for cistern | C79: Supply pipework and point. | D79: pt | E79: 7 | F79: Per documents | G79: 575 | H79: =ROUND(E79*G79,2)
A80: 05.27 | B80: Sewage point for WC | C80: Drainage pipework and point. | D80: pt | E80: 7 | F80: Per documents | G80: 805 | H80: =ROUND(E80*G80,2)
A81: 05.28 | B81: Drain point for basin and bathtub | C81: Drainage pipework and point. | D81: pt | E81: 15 | F81: Per documents | G81: 518 | H81: =ROUND(E81*G81,2)
A82: 05.29 | B82: Water and drain point for washing machine | C82: Supply and drain points. | D82: pt | E82: 2 | F82: Per documents | G82: 1035 | H82: =ROUND(E82*G82,2)
A83: 05.30 | B83: Utility (bucket) tap | C83: Installation of utility tap. | D83: pcs | E83: 2 | F83: Per documents | G83: 207 | H83: =ROUND(E83*G83,2)
A84: 05.32 | B84: Main supply lines and floor manifolds | C84: Main water supply lines and floor-level manifolds. | D84: lot | E84: 1 | F84: Per documents | G84: 23000 | H84: =ROUND(E84*G84,2)
A85: 05.33 | B85: Main sewage and drainage system | C85: Main sewage and drainage system. | D85: lot | E85: 1 | F85: Per documents | G85: 20700 | H85: =ROUND(E85*G85,2)
A86: 05.34 | B86: Water heater – installation and connection | C86: Installation and connection of water heater. | D86: pcs | E86: 2 | F86: Provisional – remeasure | G86: 1380 | H86: =ROUND(E86*G86,2) | I86: Installation only; supply by Employer
A87: 05.35 | B87: Pressure and leak tests, as-built drawings | C87: Testing of the plumbing systems and as-built documentation. | D87: lot | E87: 1 | F87: Per documents | G87: 2875 | H87: =ROUND(E87*G87,2)
A88: Total – Chapter 05 | H88: =SUM(H55:H87)
A90: Chapter 6 — Electrical Works
A91: 06.01 | B91: Standard socket point | C91: Wiring to the relevant circuit, accessory and test. | D91: pcs | E91: 119 | F91: Per documents | G91: 310 | H91: =ROUND(E91*G91,2)
A92: 06.02 | B92: Waterproof socket point | C92: Waterproof socket point (IP44 or above). | D92: pcs | E92: 51 | F92: Per documents | G92: 368 | H92: =ROUND(E92*G92,2)
A93: 06.03 | B93: Infrastructure for electric roller shutter | C93: Conduit and wiring for electric shutter operation. | D93: pcs | E93: 18 | F93: Per documents | G93: 437 | H93: =ROUND(E93*G93,2)
A94: 06.04 | B94: Shutter motor socket | C94: Socket for shutter motor. | D94: pcs | E94: 9 | F94: Per documents | G94: 253 | H94: =ROUND(E94*G94,2)
A95: 06.05 | B95: Three-phase socket point | C95: Three-phase socket point. | D95: pcs | E95: 1 | F95: Per documents | G95: 1035 | H95: =ROUND(E95*G95,2)
A96: 06.06 | B96: Extension of main distribution board | C96: Extension of the main board for the total added load. | D96: lot | E96: 1 | F96: Per documents | G96: 9775 | H96: =ROUND(E96*G96,2)
A97: 06.07 | B97: Electricity company pillar – supply and installation | C97: Supply and installation of the new electricity company pillar at the plot entrance. | D97: lot | E97: 1 | F97: Per documents | G97: 8050 | H97: =ROUND(E97*G97,2)
A98: 06.08 | B98: Handling of supply upgrade | C98: Preparing and submitting plans to the electricity company for upgrade to 3×40A and obtaining approvals. Fees and upgrade charges payable to the electricity company by the Employer. | D98: lot | E98: 1 | F98: Per documents | G98: 5175 | H98: =ROUND(E98*G98,2)
A99: 06.09 | B99: Final electrical inspection | C99: Final inspection by a certified inspector, certificate and test report. | D99: lot | E99: 1 | F99: Per documents | G99: 2875 | H99: =ROUND(E99*G99,2)
A100: 06.10 | B100: Power socket point | C100: Power socket point. | D100: pcs | E100: 9 | F100: Per documents | G100: 437 | H100: =ROUND(E100*G100,2)
A101: 06.11 | B101: Supply point for A/C unit | C101: Dedicated supply point for an A/C unit. | D101: pt | E101: 8 | F101: Provisional – remeasure | G101: 862 | H101: =ROUND(E101*G101,2)
A102: 06.12 | B102: Direct connection point | C102: Direct electrical connection point for fixed appliances. | D102: pt | E102: 6 | F102: Provisional – remeasure | G102: 598 | H102: =ROUND(E102*G102,2)
... A105: 06.15 | B105: Doorbell and push button | C105: Doorbell and push button. | D105: lot | E105: 1 | F105: Per documents | G105: 747 | H105: =ROUND(E105*G105,2)
A106: Total – Chapter 06 | H106: =SUM(H91:H105)
A108: Chapter 7 — Lighting and Light Switches
A109: 07.01 | B109: Lighting switches (single / double / triple / quad) | C109: Installation of lighting switches. | D109: pcs | E109: 55 | F109: Provisional – remeasure | G109: 172 | H109: =ROUND(E109*G109,2)
A110: 07.02 | B110: Two-way switches (single / triple) | C110: Installation of two-way switches. | D110: pcs | E110: 12 | F110: Provisional – remeasure | G110: 230 | H110: =ROUND(E110*G110,2)
A111: 07.03 | B111: Ceiling-mounted light fitting | C111: Installation, electrical connection and test. | D111: pcs | E111: 15 | F111: Per documents | G111: 253 | H111: =ROUND(E111*G111,2) | I111: Installation only; supply by Employer
A112: 07.04 | B112: Pendant light fitting | C112: Installation, suspension system, height adjustment per plan, connection and test. | D112: pcs | E112: 22 | F112: Per documents | G112: 368 | H112: =ROUND(E112*G112,2) | I112: Installation only; supply by Employer
A113: 07.05 | B113: Protected wall light fitting | C113: Installation and connection. | D113: pcs | E113: 30 | F113: Per documents | G113: 253 | H113: =ROUND(E113*G113,2) | I113: Installation only; supply by Employer
A114: 07.06 | B114: Protected recessed wall light fitting | C114: Installation and connection. | D114: pcs | E114: 35 | F114: Per documents | G114: 345 | H114: =ROUND(E114*G114,2) | I114: Installation only; supply by Employer
A115: 07.07 | B115: Recessed spot in gypsum ceiling | C115: Installation and connection. | D115: pcs | E115: 25 | F115: Per documents | G115: 98 | H115: =ROUND(E115*G115,2) | I115: Installation only; supply by Employer
A116: 07.08 | B116: Concealed LED strip | C116: Installation of concealed LED strip. | D116: pcs | E116: 11 | F116: Per documents | G116: 402 | H116: =ROUND(E116*G116,2) | I116: Installation only; supply by Employer
A117: 07.09 | B117: Recessed linear fitting in gypsum | C117: Installation of recessed linear fitting. | D117: pcs | E117: 2 | F117: Per documents | G117: 518 | H117: =ROUND(E117*G117,2) | I117: Installation only; supply by Employer
A118: 07.10 | B118: Surface-mounted linear fitting | C118: Installation of ceiling-mounted linear fitting. | D118: pcs | E118: 9 | F118: Per documents | G118: 345 | H118: =ROUND(E118*G118,2) | I118: Installation only; supply by Employer
A119: 07.11 | B119: LED strip feed point | C119: Feed point for LED strip. | D119: pcs | E119: 25 | F119: Per documents | G119: 322 | H119: =ROUND(E119*G119,2) | I119: Installation only; supply by Employer
A120: 07.12 | B120: Waterproof light fitting | C120: Installation and connection. | D120: pcs | E120: 8 | F120: Per documents | G120: 276 | H120: =ROUND(E120*G120,2) | I120: Installation only; supply by Employer
A121: 07.13 | B121: Wall light fitting | C121: Installation and connection. | D121: pcs | E121: 5 | F121: Per documents | G121: 230 | H121: =ROUND(E121*G121,2) | I121: Installation only; supply by Employer
A122: 07.14 | B122: Recessed wall light fitting | C122: Installation and connection. | D122: pcs | E122: 10 | F122: Per documents | G122: 345 | H122: =ROUND(E122*G122,2) | I122: Installation only; supply by Employer
... A127: 07.19 | B127: Recessed spot cluster in gypsum | C127: Installation of recessed spot clusters. | D127: pcs | E127: 28 | F127: Per documents | G127: 195 | H127: =ROUND(E127*G127,2) | I127: Installation only; supply by Employer
A128: 07.20 | B128: General lighting feed point | C128: General lighting feed point. | D128: pcs | E128: 14 | F128: Per documents | G128: 345 | H128: =ROUND(E128*G128,2)
A129: Total – Chapter 07 | H129: =SUM(H109:H128)
A131: Chapter 8 — Air Conditioning
...

Sheet Summary
A1: Summary of Quotation
A3: Chapter | B3: Amount (₪)
A4: 1. Preparation and Site Establishment | B4: =Quotation!H16
A5: 2. Demolition, Removals and Disposal | B5: =Quotation!H39
A6: 3. Structural Works and Extensions | B6: =Quotation!H46
A7: 4. New Block Wall Partitions | B7: =Quotation!H52
A8: 5. Plumbing, Sanitary Fixtures and Taps | B8: =Quotation!H88
A9: 6. Electrical Works | B9: =Quotation!H106
A10: 7. Lighting and Light Switches | B10: =Quotation!H129
A11: 8. Air Conditioning | B11: =Quotation!H136
A12: 9. Gypsum Partitions and Ceilings | B12: =Quotation!H143
A13: 10. Internal Waterproofing | B13: =Quotation!H150
A14: 11. Roof and Parapet Waterproofing | B14: =Quotation!H158
A15: 12. Window Sills and Door Thresholds | B15: =Quotation!H165
A16: 13. Flooring, Wall Tiling and Skirting | B16: =Quotation!H174
A17: 14. External Coloured Plaster | B17: =Quotation!H180
A18: 15. Plaster Repairs, Skim Coat and Internal Painting | B18: =Quotation!H186
A19: 16. Aluminium, Doors and Gates | B19: =Quotation!H197
A20: 17. External Development | B20: =Quotation!H204
A21: 18. Communications, Security, Intercom and Audio Infrastructure | B21: =Quotation!H212
A22: Total before discount | B22: =SUM(B4:B21)
A23: Discount | B23: =-ROUND(B22*C23,2) | C23: 0.25
A24: Total after discount, excl. VAT | B24: =B22+B23
A25: VAT | B25: =ROUND(B24*C25,2) | C25: 0.18
A26: TOTAL INCLUDING VAT | B26: =B24+B25

Sheet Notes & Exclusions
A1: # | B1: Type | C1: Note
A2: 1 | B2: Basis | C2: Quotation based on: Technical Specification Book rev. 20 (06/07/2026); architectural drawings "New Construction" – ground floor (sheet 13) and first floor (sheet 23), dated 17/09/2026; Contractor Quantity Schedule dated 24/09/2026; the Employer's bill of quantities. Where documents differ, the Quantity Schedule dated 24/09/2026 was used.
A3: 2 | B3: Quantities | C3: Items marked "Provisional – remeasure" have no quantity in the documents provided (air conditioning, switches, emergency lighting, water heaters, direct connections, communication points, roof/parapet, scaffolding). They are priced on estimated quantities and will be remeasured on site.
A4: 3 | B4: Structural | C4: Chapter 3 (balcony and pergola, gallery room, entrance and stairs, strengthening of internal stairs) is a provisional sum. The structural engineer's complete drawings were not provided; the price will be adjusted on receipt.
A5: 4 | B5: Supply | C5: Sanitary ware and taps, light fittings, air-conditioning units, water heaters, and floor / wall tiles are supplied by the Employer; the Contractor installs. Aluminium, doors, gates, shutters and stone sills are supplied and installed.
A6: 5 | B6: Exclusion | C6: Swimming pool (all works), carpentry (kitchen, bathroom and wardrobe cabinets), furniture, permits and fees, consultants' fees, and electricity company charges for the supply upgrade.
A7: 6 | B7: Exclusion | C7: Items that depend on the Employer's decisions: electric shutters (optional), garden plant types, final fixture models.
A8: 7 | B8: Tests | C8: Required tests and approvals (structural engineer, waterproofing consultant, certified electrical inspector, flood tests) are included as per the specification.
A9: 8 | B9: Commercial | C9: Validity: [__ days] | Payment terms: [__] | Price adjustment: [__]
A10: 9 | B10: Discount | C10: A discount of 25% on the total of the quotation is shown in the Summary sheet.

Sheet Programme
A1: Phase | B1: Start | C1: Finish
A2: Contract award and orders placed | B2: 46327 | C2: 46327
A3: Site establishment and approvals to demolish | B3: 46328 | C3: 46341
A4: Demolition and removals | B4: 46342 | C4: 46369
A5: Scaffolding erected / removed | B5: 46342 | C5: 46475
A6: Structural works and extensions | B6: 46370 | C6: 46420
A7: Roof and parapet | B7: 46370 | C7: 46405
A8: MEP rough-in and tests | B8: 46376 | C8: 46406
A9: Gypsum and waterproofing | B9: 46407 | C9: 46448
A10: Facade and external works | B10: 46421 | C10: 46484
A11: Interior finishes (tiling, plaster, paint, fittings) | B11: 46422 | C11: 46525
A12: Inspections, handover preparation | B12: 46526 | C12: 46546
A13: Handover | B13: 46546 | C13: 46546
A15: Indicative programme, working week Sunday–Thursday, start 01/11/2026. Excludes holidays and weather delays. Total duration approx. 31 weeks.
