Workbook

Sheet Presupuesto
A1: PRESUPUESTO — Reforma y ampliación, calle Shlonsky 53, Haifa
A2: Propiedad: Zohar Mor Yosef y Rami Dana | Contratista: [Nombre del contratista] | Fecha: 14/10/2026 | Presupuesto n.º: [__]
A3: Todos los importes en EUR (€), sin IVA, base de precios octubre 2026. Los precios unitarios incluyen gastos generales y beneficio del contratista (15 %).
A5: Partida | B5: Designación | C5: Descripción | D5: Unidad | E5: Cant. | F5: Precio unitario | G5: Importe | H5: Observaciones
A6: Capítulo 1 — Preparación e instalación de obra
A7: 01.01 | B7: Instalación de obra | C7: Habilitación de zonas de trabajo y acopio, instalaciones para operarios y coordinación de accesos. | D7: global | E7: 1 | F7: 1420 | G7: =IF(AND(ISNUMBER(E7),ISNUMBER(F7)),ROUND(E7*F7,2),"") -> 1420
A8: 01.02 | B8: Vallado, señalización y seguridad de obra | C8: Vallado provisional, carteles de obra y de peligro y medidas de seguridad necesarias durante la obra. | D8: global | E8: 1 | F8: 710 | G8: =IF(AND(ISNUMBER(E8),ISNUMBER(F8)),ROUND(E8*F8,2),"") -> 710
A9: 01.03 | B9: Acometida provisional de agua | C9: Acometida provisional de agua desde el punto autorizado, con comprobación. | D9: global | E9: 1 | F9: 266 | G9: =IF(AND(ISNUMBER(E9),ISNUMBER(F9)),ROUND(E9*F9,2),"") -> 266
A10: 01.04 | B10: Acometida eléctrica provisional | C10: Acometida eléctrica provisional realizada por electricista autorizado, con protecciones y comprobación. | D10: global | E10: 1 | F10: 530 | G10: =IF(AND(ISNUMBER(E10),ISNUMBER(F10)),ROUND(E10*F10,2),"") -> 530
A11: 01.05 | B11: Protección de elementos existentes | C11: Protecciones de suelos, huecos, ventanas, escaleras, barandillas, paredes y plantas que se conservan. | D11: global | E11: 1 | F11: 890 | G11: =IF(AND(ISNUMBER(E11),ISNUMBER(F11)),ROUND(E11*F11,2),"") -> 890
A12: 01.06 | B12: Replanteo, verificación y marcado láser | C12: Medición del edificio existente, verificación con los planos de arquitectura e instalaciones y replanteo de posiciones y niveles. | D12: global | E12: 1 | F12: 530 | G12: =IF(AND(ISNUMBER(E12),ISNUMBER(F12)),ROUND(E12*F12,2),"") -> 530
A13: 01.07 | B13: Contenedor de residuos y zona de acopio | C13: Colocación de contenedor y zona de acopio; retirada de residuos a vertedero autorizado. | D13: global | E13: 1 | F13: 1600 | G13: =IF(AND(ISNUMBER(E13),ISNUMBER(F13)),ROUND(E13*F13,2),"") -> 1600
A14: 01.08 | B14: Limpieza periódica de obra | C14: Limpieza periódica de las zonas de trabajo y de paso durante toda la obra. | D14: global | E14: 1 | F14: 1600 | G14: =IF(AND(ISNUMBER(E14),ISNUMBER(F14)),ROUND(E14*F14,2),"") -> 1600
A15: 01.09 | B15: Andamio exterior | C15: Montaje, alquiler durante la obra (unos 4,5 meses), mantenimiento y desmontaje de andamio exterior homologado alrededor de las fachadas, para el corte de los marcos de hormigón decorativos y los trabajos de revoco de fachada. | D15: m² | E15: 225 | F15: 32 | G15: =IF(AND(ISNUMBER(E15),ISNUMBER(F15)),ROUND(E15*F15,2),"") -> 7200 | H15: Cantidad provisional – se medirá en obra
A16: Total – Capítulo 1 | G16: =IF(COUNT(G7:G15)=0,"",SUM(G7:G15)) -> 14746
A18: Capítulo 2 — Demoliciones, desmontajes y retirada de residuos
A19: 02.01 | B19: Demolición de muros y tabiques – sótano | C19: Demolición de muros y tabiques existentes según planos de demolición. | D19: m² | E19: 62 | F19: 21.5 | G19: =IF(AND(ISNUMBER(E19),ISNUMBER(F19)),ROUND(E19*F19,2),"") -> 1333
A20: 02.02 | B20: Demolición de muros y tabiques – planta baja | C20: Demolición de muros y tabiques existentes según planos de demolición. | D20: m² | E20: 51 | F20: 21.5 | G20: =IF(AND(ISNUMBER(E20),ISNUMBER(F20)),ROUND(E20*F20,2),"") -> 1096.5
A21: 02.03 | B21: Demolición de muros y tabiques – primera planta | C21: Demolición de muros y tabiques existentes según planos de demolición. | D21: m² | E21: 85 | F21: 21.5 | G21: =IF(AND(ISNUMBER(E21),ISNUMBER(F21)),ROUND(E21*F21,2),"") -> 1827.5
A22: 02.04 | B22: Desmontaje de falsos techos de yeso laminado | C22: Desmontaje de los falsos techos de yeso laminado existentes. | D22: m² | E22: 10 | F22: 8.9 | G22: =IF(AND(ISNUMBER(E22),ISNUMBER(F22)),ROUND(E22*F22,2),"") -> 89
A23: 02.05 | B23: Levantado de pavimentos existentes | C23: Levantado de los pavimentos existentes. | D23: m² | E23: 40 | F23: 16 | G23: =IF(AND(ISNUMBER(E23),ISNUMBER(F23)),ROUND(E23*F23,2),"") -> 640
A24: 02.06 | B24: Desmontaje de muebles de cocina existentes | C24: Desmontaje completo de los muebles de cocina existentes. | D24: global | E24: 1 | F24: 355 | G24: =IF(AND(ISNUMBER(E24),ISNUMBER(F24)),ROUND(E24*F24,2),"") -> 355
A25: 02.07 | B25: Desmontaje de otros armarios y carpintería | C25: Desmontaje de otros armarios y elementos de carpintería existentes. | D25: ud | E25: 1 | F25: 444 | G25: =IF(AND(ISNUMBER(E25),ISNUMBER(F25)),ROUND(E25*F25,2),"") -> 444
A26: 02.08 | B26: Desmontaje de ventanas de aluminio y persianas existentes | C26: Desmontaje completo de las ventanas de aluminio y persianas existentes. | D26: global | E26: 1 | F26: 1060 | G26: =IF(AND(ISNUMBER(E26),ISNUMBER(F26)),ROUND(E26*F26,2),"") -> 1060
A27: 02.09 | B27: Desmontaje de puertas interiores y de entrada y sus marcos | C27: Desmontaje completo de las puertas interiores y de entrada y sus marcos. | D27: global | E27: 1 | F27: 620 | G27: =IF(AND(ISNUMBER(E27),ISNUMBER(F27)),ROUND(E27*F27,2),"") -> 620
A28: 02.10 | B28: Desmontaje de baños, aseos y aparatos sanitarios | C28: Desmontaje completo de baños, aseos y aparatos sanitarios existentes. | D28: global | E28: 1 | F28: 1420 | G28: =IF(AND(ISNUMBER(E28),ISNUMBER(F28)),ROUND(E28*F28,2),"") -> 1420
A29: 02.11 | B29: Desmontaje de puntos, mecanismos y luminarias eléctricas | C29: Desmontaje de los puntos, mecanismos y luminarias eléctricas existentes. | D29: global | E29: 1 | F29: 710 | G29: =IF(AND(ISNUMBER(E29),ISNUMBER(F29)),ROUND(E29*F29,2),"") -> 710
A30: 02.12 | B30: Desmontaje de fontanería vista existente | C30: Desmontaje de las tuberías de fontanería vistas existentes. | D30: global | E30: 1 | F30: 530 | G30: =IF(AND(ISNUMBER(E30),ISNUMBER(F30)),ROUND(E30*F30,2),"") -> 530
... A38: 02.20 | B38: Demolición de la escalera de entrada existente | C38: Demolición de la escalera de entrada existente, incluido corte, carga y retirada, previa a los nuevos escalones volados. | D38: global | E38: 1 | F38: 530 | G38: =IF(AND(ISNUMBER(E38),ISNUMBER(F38)),ROUND(E38*F38,2),"") -> 530
A39: 02.21 | B39: Retirada de césped y plantas de jardín | C39: Retirada del césped, arbustos y plantas de jardín existentes en las zonas de urbanización, incluidas raíces, carga y retirada. | D39: m² | E39: 65 | F39: 6.2 | G39: =IF(AND(ISNUMBER(E39),ISNUMBER(F39)),ROUND(E39*F39,2),"") -> 403 | H39: Cantidad provisional – se medirá en obra
A40: Total – Capítulo 2 | G40: =IF(COUNT(G19:G39)=0,"",SUM(G19:G39)) -> 21385.5
A42: Capítulo 3 — Obras de estructura y ampliaciones
A43: 03.01 | B43: Ampliación del balcón del salón y nueva pérgola | C43: Obra estructural completa según planos y especificaciones del ingeniero de estructuras. | D43: global | E43: 1 | F43: 12400 | G43: =IF(AND(ISNUMBER(E43),ISNUMBER(F43)),ROUND(E43*F43,2),"") -> 12400 | H43: Importe global – se ajustará al recibir los planos de estructura
A44: 03.02 | B44: Nueva habitación en el nivel de galería | C44: Obra estructural completa de la habitación según planos de estructura y arquitectura, incluidas conexiones con la estructura existente y huecos. Acabados e instalaciones en sus capítulos. | D44: global | E44: 1 | F44: 21300 | G44: =IF(AND(ISNUMBER(E44),ISNUMBER(F44)),ROUND(E44*F44,2),"") -> 21300 | H44: Importe global – se ajustará al recibir los planos de estructura
A45: 03.03 | B45: Nueva entrada y nueva escalera | C45: Obra completa de la nueva entrada y escalera según el ingeniero de estructuras. | D45: global | E45: 1 | F45: 6700 | G45: =IF(AND(ISNUMBER(E45),ISNUMBER(F45)),ROUND(E45*F45,2),"") -> 6700 | H45: Importe global – se ajustará al recibir los planos de estructura
A46: 03.04 | B46: Refuerzo de la escalera interior existente | C46: Refuerzo según el ingeniero de estructuras, tras retirar la barandilla. | D46: global | E46: 1 | F46: 3190 | G46: =IF(AND(ISNUMBER(E46),ISNUMBER(F46)),ROUND(E46*F46,2),"") -> 3190 | H46: Importe global – se ajustará al recibir los planos de estructura
A47: 03.05 | B47: Escalones de entrada volados | C47: 12 nuevos escalones volados (en voladizo) en la entrada, en sustitución de la escalera existente, de unos 1,15 m de ancho, con armado, anclajes y preparación para el revestimiento, según planos de estructura y arquitectura. Revestimiento en la partida 13.08. | D47: ud | E47: 12 | F47: 497 | G47: =IF(AND(ISNUMBER(E47),ISNUMBER(F47)),ROUND(E47*F47,2),"") -> 5964 | H47: Importe global – se ajustará al recibir los planos de estructura; Medida definitiva según lo existente en obra
A48: Total – Capítulo 3 | G48: =IF(COUNT(G43:G47)=0,"",SUM(G43:G47)) -> 49554
A50: Capítulo 4 — Nuevos muros de bloque
A51: 04.01 | B51: Nuevos muros de bloque (20 cm) – sótano | C51: Muros de bloque según planos. | D51: m² | E51: 6.3 | F51: 53 | G51: =IF(AND(ISNUMBER(E51),ISNUMBER(F51)),ROUND(E51*F51,2),"") -> 333.9
A52: 04.02 | B52: Nuevos muros de bloque (20 cm) – planta baja | C52: Muros de bloque según planos. | D52: m² | E52: 17.7 | F52: 53 | G52: =IF(AND(ISNUMBER(E52),ISNUMBER(F52)),ROUND(E52*F52,2),"") -> 938.1
A53: 04.03 | B53: Nuevos muros de bloque (20 cm) – primera planta y galería | C53: Muros de bloque según planos. | D53: m² | E53: 2.08 | F53: 53 | G53: =IF(AND(ISNUMBER(E53),ISNUMBER(F53)),ROUND(E53*F53,2),"") -> 110.24
A54: Total – Capítulo 4 | G54: =IF(COUNT(G51:G53)=0,"",SUM(G51:G53)) -> 1382.24
A56: Capítulo 5 — Fontanería, aparatos sanitarios y griferías
A57: 05.01 | B57: Inodoro suspendido | C57: Instalación, fijación al bastidor, conexión a descarga y desagüe, y pruebas. | D57: ud | E57: 7 | F57: 142 | G57: =IF(AND(ISNUMBER(E57),ISNUMBER(F57)),ROUND(E57*F57,2),"") -> 994 | H57: Solo instalación; suministro por la propiedad
A58: 05.02 | B58: Cisterna empotrada y bastidor soporte | C58: Instalación, anclaje, conexión de agua y al inodoro y prueba de estanqueidad antes de cerrar el revestimiento. | D58: ud | E58: 7 | F58: 195 | G58: =IF(AND(ISNUMBER(E58),ISNUMBER(F58)),ROUND(E58*F58,2),"") -> 1365 | H58: Solo instalación; suministro por la propiedad
A59: 05.03 | B59: Pulsador de descarga | C59: Instalación del pulsador compatible con la cisterna empotrada y comprobación. | D59: ud | E59: 7 | F59: 26.5 | G59: =IF(AND(ISNUMBER(E59),ISNUMBER(F59)),ROUND(E59*F59,2),"") -> 185.5 | H59: Solo instalación; suministro por la propiedad
A60: 05.04 | B60: Asiento de inodoro de cierre amortiguado | C60: Instalación y ajuste. | D60: ud | E60: 7 | F60: 26.5 | G60: =IF(AND(ISNUMBER(E60),ISNUMBER(F60)),ROUND(E60*F60,2),"") -> 185.5 | H60: Solo instalación; suministro por la propiedad
A61: 05.05 | B61: Lavabo de pie | C61: Instalación, fijación, conexión al desagüe y sellado. | D61: ud | E61: 1 | F61: 106 | G61: =IF(AND(ISNUMBER(E61),ISNUMBER(F61)),ROUND(E61*F61,2),"") -> 106 | H61: Solo instalación; suministro por la propiedad
A62: 05.06 | B62: Grifo de pared | C62: Instalación y conexión. | D62: ud | E62: 6 | F62: 53 | G62: =IF(AND(ISNUMBER(E62),ISNUMBER(F62)),ROUND(E62*F62,2),"") -> 318 | H62: Solo instalación; suministro por la propiedad
A63: 05.07 | B63: Rociador de ducha tipo lluvia | C63: Instalación y conexión. | D63: ud | E63: 6 | F63: 80 | G63: =IF(AND(ISNUMBER(E63),ISNUMBER(F63)),ROUND(E63*F63,2),"") -> 480 | H63: Solo instalación; suministro por la propiedad
A64: 05.08 | B64: Válvula desviadora de 3 vías | C64: Instalación de válvula desviadora de 3 vías (tipo Interpoz) y su acabado. | D64: ud | E64: 10 | F64: 80 | G64: =IF(AND(ISNUMBER(E64),ISNUMBER(F64)),ROUND(E64*F64,2),"") -> 800 | H64: Solo instalación; suministro por la propiedad
A65: 05.09 | B65: Válvula desviadora de 4 vías | C65: Instalación de válvula desviadora de 4 vías (tipo Interpoz) y su acabado. | D65: ud | E65: 2 | F65: 106 | G65: =IF(AND(ISNUMBER(E65),ISNUMBER(F65)),ROUND(E65*F65,2),"") -> 212 | H65: Solo instalación; suministro por la propiedad
A66: 05.10 | B66: Soporte de teleducha | C66: Instalación del soporte de teleducha. | D66: ud | E66: 7 | F66: 44.5 | G66: =IF(AND(ISNUMBER(E66),ISNUMBER(F66)),ROUND(E66*F66,2),"") -> 311.5 | H66: Solo instalación; suministro por la propiedad
A67: 05.11 | B67: Canaleta de desagüe lineal 10/10 (duchas) | C67: Instalación y conexión de la canaleta. | D67: ud | E67: 5 | F67: 115 | G67: =IF(AND(ISNUMBER(E67),ISNUMBER(F67)),ROUND(E67*F67,2),"") -> 575 | H67: Solo instalación; suministro por la propiedad
A68: 05.12 | B68: Rebosadero 110 para bañera | C68: Instalación del rebosadero. | D68: ud | E68: 1 | F68: 266 | G68: =IF(AND(ISNUMBER(E68),ISNUMBER(F68)),ROUND(E68*F68,2),"") -> 266 | H68: Solo instalación; suministro por la propiedad
... A70: 05.15 | B70: Grifo llenabañeras | C70: Instalación del grifo llenabañeras. | D70: ud | E70: 1 | F70: 177 | G70: =IF(AND(ISNUMBER(E70),ISNUMBER(F70)),ROUND(E70*F70,2),"") -> 177 | H70: Solo instalación; suministro por la propiedad
A71: 05.16 | B71: Fregadero de cocina | C71: Instalado por el proveedor de la encimera. | D71: ud | E71: 3 | F71: Por el proveedor de la encimera | G71: =IF(AND(ISNUMBER(E71),ISNUMBER(F71)),ROUND(E71*F71,2),"")
A72: 05.17 | B72: Grifo de cocina extraíble | C72: Instalación, conexión y prueba de funcionamiento. | D72: ud | E72: 5 | F72: 80 | G72: =IF(AND(ISNUMBER(E72),ISNUMBER(F72)),ROUND(E72*F72,2),"") -> 400 | H72: Solo instalación; suministro por la propiedad
A73: 05.18 | B73: Fregadero de cocina exterior | C73: Instalado por el proveedor de la encimera. | D73: ud | E73: 2 | F73: Por el proveedor de la encimera | G73: =IF(AND(ISNUMBER(E73),ISNUMBER(F73)),ROUND(E73*F73,2),"")
A74: 05.19 | B74: Grifo exterior extraíble | C74: Instalación y conexión. | D74: ud | E74: 2 | F74: 80 | G74: =IF(AND(ISNUMBER(E74),ISNUMBER(F74)),ROUND(E74*F74,2),"") -> 160 | H74: Solo instalación; suministro por la propiedad
A75: 05.20 | B75: Lavabo sobre encimera / pila – aseo de invitados | C75: Instalación y conexión. | D75: ud | E75: 1 | F75: 115 | G75: =IF(AND(ISNUMBER(E75),ISNUMBER(F75)),ROUND(E75*F75,2),"") -> 115 | H75: Solo instalación; suministro por la propiedad
A76: 05.21 | B76: Grifo tipo « Nil » | C76: Instalación del grifo. | D76: ud | E76: 11 | F76: 32 | G76: =IF(AND(ISNUMBER(E76),ISNUMBER(F76)),ROUND(E76*F76,2),"") -> 352 | H76: Solo instalación; suministro por la propiedad
A77: 05.22 | B77: Grifo con mueble de baño – conjunto | C77: Instalación del grifo y del mueble de baño como conjunto. | D77: ud | E77: 1 | F77: 319 | G77: =IF(AND(ISNUMBER(E77),ISNUMBER(F77)),ROUND(E77*F77,2),"") -> 319 | H77: Solo instalación; suministro por la propiedad
A78: 05.23 | B78: Rebosadero exterior 60 | C78: Instalación del rebosadero exterior. | D78: ud | E78: 1 | F78: 213 | G78: =IF(AND(ISNUMBER(E78),ISNUMBER(F78)),ROUND(E78*F78,2),"") -> 213 | H78: Solo instalación; suministro por la propiedad
A79: 05.24 | B79: Fregadero de bar | C79: Instalación y conexión. | D79: ud | E79: 2 | F79: 98 | G79: =IF(AND(ISNUMBER(E79),ISNUMBER(F79)),ROUND(E79*F79,2),"") -> 196 | H79: Solo instalación; suministro por la propiedad
A80: 05.25 | B80: Punto de agua fría y caliente | C80: Tubería de suministro y punto. | D80: pt | E80: 23 | F80: 213 | G80: =IF(AND(ISNUMBER(E80),ISNUMBER(F80)),ROUND(E80*F80,2),"") -> 4899
A81: 05.26 | B81: Punto de agua fría para cisterna | C81: Tubería de suministro y punto. | D81: pt | E81: 7 | F81: 89 | G81: =IF(AND(ISNUMBER(E81),ISNUMBER(F81)),ROUND(E81*F81,2),"") -> 623
A82: 05.27 | B82: Punto de saneamiento para inodoro | C82: Tubería de desagüe y punto. | D82: pt | E82: 7 | F82: 124 | G82: =IF(AND(ISNUMBER(E82),ISNUMBER(F82)),ROUND(E82*F82,2),"") -> 868
A83: 05.28 | B83: Punto de desagüe para lavabo y bañera | C83: Tubería de desagüe y punto. | D83: pt | E83: 15 | F83: 80 | G83: =IF(AND(ISNUMBER(E83),ISNUMBER(F83)),ROUND(E83*F83,2),"") -> 1200
A84: 05.29 | B84: Punto de agua y desagüe para lavadora | C84: Puntos de suministro y desagüe. | D84: pt | E84: 2 | F84: 160 | G84: =IF(AND(ISNUMBER(E84),ISNUMBER(F84)),ROUND(E84*F84,2),"") -> 320
A85: 05.30 | B85: Grifo de servicio | C85: Instalación del grifo de servicio. | D85: ud | E85: 2 | F85: 32 | G85: =IF(AND(ISNUMBER(E85),ISNUMBER(F85)),ROUND(E85*F85,2),"") -> 64
A86: 05.32 | B86: Líneas generales de suministro y colectores por planta | C86: Líneas generales de agua y colectores a nivel de planta. | D86: global | E86: 1 | F86: 3550 | G86: =IF(AND(ISNUMBER(E86),ISNUMBER(F86)),ROUND(E86*F86,2),"") -> 3550
A87: 05.33 | B87: Red principal de saneamiento y drenaje | C87: Red principal de saneamiento y drenaje. | D87: global | E87: 1 | F87: 3190 | G87: =IF(AND(ISNUMBER(E87),ISNUMBER(F87)),ROUND(E87*F87,2),"") -> 3190
A88: 05.34 | B88: Termo de agua – instalación y conexión | C88: Instalación y conexión del termo de agua. | D88: ud | E88: 1 | F88: 213 | G88: =IF(AND(ISNUMBER(E88),ISNUMBER(F88)),ROUND(E88*F88,2),"") -> 213 | H88: Solo instalación; suministro por la propiedad
A89: 05.35 | B89: Pruebas de presión y estanqueidad, planos finales de obra | C89: Pruebas de las instalaciones de fontanería y documentación final de obra. | D89: global | E89: 1 | F89: 444 | G89: =IF(AND(ISNUMBER(E89),ISNUMBER(F89)),ROUND(E89*F89,2),"") -> 444
A90: Total – Capítulo 5 | G90: =IF(COUNT(G57:G89)=0,"",SUM(G57:G89)) -> 23491.5
A92: Capítulo 6 — Instalación eléctrica
A93: 06.01 | B93: Punto de enchufe estándar | C93: Cableado al circuito correspondiente, mecanismo y comprobación. | D93: ud | E93: 119 | F93: 47 | G93: =IF(AND(ISNUMBER(E93),ISNUMBER(F93)),ROUND(E93*F93,2),"") -> 5593
A94: 06.02 | B94: Punto de enchufe estanco | C94: Punto de enchufe estanco (IP44 o superior). | D94: ud | E94: 51 | F94: 56 | G94: =IF(AND(ISNUMBER(E94),ISNUMBER(F94)),ROUND(E94*F94,2),"") -> 2856
A95: 06.03 | B95: Preinstalación para persiana eléctrica | C95: Canalización y cableado para el accionamiento de la persiana eléctrica. | D95: ud | E95: 18 | F95: 66 | G95: =IF(AND(ISNUMBER(E95),ISNUMBER(F95)),ROUND(E95*F95,2),"") -> 1188
A96: 06.05 | B96: Punto de enchufe trifásico | C96: Punto de enchufe trifásico. | D96: ud | E96: 1 | F96: 157 | G96: =IF(AND(ISNUMBER(E96),ISNUMBER(F96)),ROUND(E96*F96,2),"") -> 157
A97: 06.06 | B97: Ampliación del cuadro eléctrico principal | C97: Ampliación del cuadro principal para la carga total añadida. | D97: global | E97: 1 | F97: 1510 | G97: =IF(AND(ISNUMBER(E97),ISNUMBER(F97)),ROUND(E97*F97,2),"") -> 1510
A98: 06.07 | B98: Pilar de la compañía eléctrica – suministro e instalación | C98: Suministro e instalación del nuevo pilar de la compañía eléctrica en la entrada de la parcela. | D98: global | E98: 1 | F98: 1240 | G98: =IF(AND(ISNUMBER(E98),ISNUMBER(F98)),ROUND(E98*F98,2),"") -> 1240
A99: 06.09 | B99: Inspección eléctrica final | C99: Inspección final por técnico autorizado, certificado e informe de pruebas. | D99: global | E99: 1 | F99: 444 | G99: =IF(AND(ISNUMBER(E99),ISNUMBER(F99)),ROUND(E99*F99,2),"") -> 444
A100: 06.10 | B100: Punto de toma de fuerza | C100: Punto de toma de fuerza. | D100: ud | E100: 9 | F100: 66 | G100: =IF(AND(ISNUMBER(E100),ISNUMBER(F100)),ROUND(E100*F100,2),"") -> 594
A101: 06.11 | B101: Punto de alimentación para aire acondicionado | C101: Punto de alimentación dedicado para una unidad de aire acondicionado. | D101: pt | E101: 8 | F101: 131 | G101: =IF(AND(ISNUMBER(E101),ISNUMBER(F101)),ROUND(E101*F101,2),"") -> 1048
A102: 06.12 | B102: Conexión directa al cuadro – encimera, horno y electrodomésticos dedicados | C102: Conexión directa al cuadro en línea dedicada con protección independiente para cada aparato (encimera, horno, lavavajillas, secadora y otros), incluidos cable, canalización, conexión final y pruebas. | D102: global | E102: 1 | F102: 610 | G102: =IF(AND(ISNUMBER(E102),ISNUMBER(F102)),ROUND(E102*F102,2),"") -> 610
A103: 06.13 | B103: Interruptor de termo con piloto | C103: Interruptor de termo con piloto luminoso. | D103: ud | E103: 1 | F103: 61 | G103: =IF(AND(ISNUMBER(E103),ISNUMBER(F103)),ROUND(E103*F103,2),"") -> 61
A104: Total – Capítulo 6 | G104: =IF(COUNT(G93:G103)=0,"",SUM(G93:G103)) -> 15301
A106: Capítulo 7 — Iluminación e interruptores
A107: 07.01 | B107: Interruptores de alumbrado (simples) | C107: Instalación de interruptores de alumbrado. | D107: ud | E107: 62 | F107: 26 | G107: =IF(AND(ISNUMBER(E107),ISNUMBER(F107)),ROUND(E107*F107,2),"") -> 1612
A108: 07.02 | B108: Conmutadores | C108: Instalación de conmutadores. | D108: ud | E108: 16 | F108: 35 | G108: =IF(AND(ISNUMBER(E108),ISNUMBER(F108)),ROUND(E108*F108,2),"") -> 560
A109: 07.02a | B109: Conmutador de cruce | C109: Instalación de un conmutador de cruce en un circuito de alumbrado controlado desde tres o más puntos, entre los conmutadores, incluidos mecanismo, cableado intermedio y comprobación. | D109: ud | E109: 3 | F109: 42 | G109: =IF(AND(ISNUMBER(E109),ISNUMBER(F109)),ROUND(E109*F109,2),"") -> 126
A110: 07.03 | B110: Luminaria de techo superficial | C110: Instalación, conexión eléctrica y comprobación. | D110: ud | E110: 15 | F110: 38.5 | G110: =IF(AND(ISNUMBER(E110),ISNUMBER(F110)),ROUND(E110*F110,2),"") -> 577.5 | H110: Solo instalación; suministro por la propiedad
A111: 07.04 | B111: Luminaria colgante | C111: Instalación, sistema de suspensión, ajuste de altura según plano, conexión y comprobación. | D111: ud | E111: 22 | F111: 56 | G111: =IF(AND(ISNUMBER(E111),ISNUMBER(F111)),ROUND(E111*F111,2),"") -> 1232 | H111: Solo instalación; suministro por la propiedad
A112: 07.05 | B112: Aplique de pared protegido | C112: Instalación y conexión. | D112: ud | E112: 30 | F112: 38.5 | G112: =IF(AND(ISNUMBER(E112),ISNUMBER(F112)),ROUND(E112*F112,2),"") -> 1155 | H112: Solo instalación; suministro por la propiedad
A113: 07.06 | B113: Luminaria empotrada en pared protegida | C113: Instalación y conexión. | D113: ud | E113: 35 | F113: 52 | G113: =IF(AND(ISNUMBER(E113),ISNUMBER(F113)),ROUND(E113*F113,2),"") -> 1820 | H113: Solo instalación; suministro por la propiedad
A114: 07.07 | B114: Foco empotrado en techo de yeso laminado | C114: Instalación y conexión. | D114: ud | E114: 25 | F114: 15 | G114: =IF(AND(ISNUMBER(E114),ISNUMBER(F114)),ROUND(E114*F114,2),"") -> 375 | H114: Solo instalación; suministro por la propiedad
A115: 07.08 | B115: Tira LED oculta | C115: Instalación de tira LED oculta. | D115: ud | E115: 11 | F115: 61 | G115: =IF(AND(ISNUMBER(E115),ISNUMBER(F115)),ROUND(E115*F115,2),"") -> 671 | H115: Solo instalación; suministro por la propiedad
...

Sheet Resumen
A1: Resumen del presupuesto
A3: Capítulo | B3: Importe | C3: % del total
A4: 1. Preparación e instalación de obra | B4: ='Presupuesto'!G16 -> 14746 | C4: =IF($B$18=0,0,B4/$B$18) -> 0.060761164
A5: 2. Demoliciones, desmontajes y retirada de residuos | B5: ='Presupuesto'!G40 -> 21385.5 | C5: =IF($B$18=0,0,B5/$B$18) -> 0.088119346
A6: 3. Obras de estructura y ampliaciones | B6: ='Presupuesto'!G48 -> 49554 | C6: =IF($B$18=0,0,B6/$B$18) -> 0.20418817
A7: 4. Nuevos muros de bloque | B7: ='Presupuesto'!G54 -> 1382.24 | C7: =IF($B$18=0,0,B7/$B$18) -> 0.0056955454
A8: 5. Fontanería, aparatos sanitarios y griferías | B8: ='Presupuesto'!G90 -> 23491.5 | C8: =IF($B$18=0,0,B8/$B$18) -> 0.096797158
A9: 6. Instalación eléctrica | B9: ='Presupuesto'!G104 -> 15301 | C9: =IF($B$18=0,0,B9/$B$18) -> 0.063048052
A10: 7. Iluminación e interruptores | B10: ='Presupuesto'!G126 -> 15051 | C10: =IF($B$18=0,0,B10/$B$18) -> 0.062017923
A11: 9. Tabiques y techos de yeso laminado | B11: ='Presupuesto'!G133 -> 7450 | C11: =IF($B$18=0,0,B11/$B$18) -> 0.030697862
A12: 10. Impermeabilización interior | B12: ='Presupuesto'!G139 -> 5653 | C12: =IF($B$18=0,0,B12/$B$18) -> 0.023293291
A13: 12. Alféizares y sellado de ventanas | B13: ='Presupuesto'!G145 -> 3219.89 | C13: =IF($B$18=0,0,B13/$B$18) -> 0.013267616
A14: 13. Pavimentos, alicatados y revestimientos | B14: ='Presupuesto'!G155 -> 28510.6 | C14: =IF($B$18=0,0,B14/$B$18) -> 0.11747845
A15: 14. Enlucidos, alisados y pintura | B15: ='Presupuesto'!G161 -> 19093.5 | C15: =IF($B$18=0,0,B15/$B$18) -> 0.078675118
A16: 17. Obras exteriores | B16: ='Presupuesto'!G169 -> 13470 | C16: =IF($B$18=0,0,B16/$B$18) -> 0.055503383
A17: 21. Piscina | B17: ='Presupuesto'!G176 -> 24379.68 | C17: =IF($B$18=0,0,B17/$B$18) -> 0.10045692
A18: Total sin IVA | B18: =SUM(B4:B17) -> 242687.91
A19: IVA (21%) | B19: ='Presupuesto'!G179 -> 50964.46
A20: TOTAL CON IVA | B20: =B18+B19 -> 293652.37

Sheet Condiciones y exclusiones
A1: # | B1: Condiciones y exclusiones
A2: 1 | B2: Base del presupuesto | C2: El presupuesto se basa en el Pliego Técnico (rev. 20, 06/07/2026), los planos de arquitectura «Obra nueva» – planta baja y primera planta (17/09/2026) y el cuadro de cantidades del contratista de 24/09/2026. En caso de discrepancia prevalece el cuadro del 24/09/2026.
A3: 2 | B3: Cantidades | C3: Cantidades según los documentos anteriores. Las partidas «provisionales» o «según medición en obra» se medirán; la liquidación final seguirá las cantidades realmente ejecutadas.
A4: 3 | B4: Estructura | C4: El capítulo 3 (balcón y pérgola, habitación en galería, entrada y escalera, refuerzo de la escalera interior) es un importe global según planos del ingeniero de estructuras; el precio se ajustará al recibir los planos completos.
A5: 4 | B5: Suministro | C5: Aparatos sanitarios y griferías, luminarias, unidades de aire acondicionado, termos y baldosas de suelo y pared los suministra la propiedad; el contratista los instala. Los fregaderos de cocina los instala el proveedor de la encimera.
A6: 5 | B6: Exclusiones | C6: Carpintería (muebles de cocina, baño y armarios); ventanas y puertas de aluminio, puertas interiores y de entrada, cancelas y persianas; trabajos de peto de cubierta; mobiliario; licencias y tasas; honorarios de consultores (estructura, impermeabilización, iluminación); cargos de la compañía eléctrica por ampliación de potencia. La piscina SÍ está incluida (capítulo 21).
A7: 6 | B7: Pruebas | C7: Las pruebas y aprobaciones exigidas (ingeniero de estructuras, consultor de impermeabilización, inspector eléctrico autorizado, pruebas de inundación y presión) están incluidas.
A8: 7 | B8: Precios | C8: Precios en EUR, sin IVA, base octubre 2026, sin revisión salvo pacto en contrario.
A9: 8 | B9: Condiciones comerciales | C9: Validez: [__ días] | Forma de pago: [__] | Plazo: [__]

Sheet Estudio de mercado (interno)
A1: Categoría | B1: Datos de mercado encontrados (2026) | C1: Fuentes
A2: Tabique de yeso laminado | B2: 25–55 €/m² (media 30 €/m²), material y mano de obra | C2: habitissimo.es/presupuestos/pladur ; habitissimo.es/presupuestos/tabique-pladur
A3: Suelo porcelánico (colocación) | B3: 28–60 €/m² (media 45 €/m², material incluido); baño rectificado 50 €/m² | C3: habitissimo.es/presupuestos/suelo-porcelanico
A4: Punto de luz / enchufe | B4: 30–60 € por punto (referencia sin fecha); electricista ≈ 50 €/h | C4: cronoshare.com (prensa Valencia) ; sensorautomotriz.com/preguntas-frecuentes/cuanto-vale-poner-un-enchufe
A5: Pintura interior | B5: 8–12 €/m² (referencia sin fecha) | C5: trustlocal.es/coste/pintor-coste/
A6: Andamio | B6: ≈ 22 €/m² (partida de presupuesto público, Zaragoza, montaje y alquiler); otra partida ≈ 10 €/m² montaje y desmontaje | C6: zaragoza.es (anuncio 85085) ; caib.es (documento 485932)
A7: Piscina de obra | B7: 8×4×1,6 m en hormigón armado ≈ 10.000 € (tabla sin fecha); proyectado ≈ 16.000 € (foro); estimación propia 14.000–20.000 € con revestimiento y equipos | C7: habitissimo.es/presupuestos/construccion-piscinas ; todoexpertos.com/categorias/casa-y-jardin/piscinas
A8: Mano de obra | B8: oficial de primera: 26–36 €/h tarifa de venta (zonas medias), 36–50 €/h País Vasco/Navarra | C8: presupix.com/blog/precio-hora-oficial-construccion ; caasa.es/precios/
A9: Tipo de cambio | B9: ≈ 3,50 ILS por 1 EUR (≈ 3,46 a principios de agosto de 2026; octubre = previsiones) | C9: ofx.com ; b-sharpe.com
A11: Método: cada precio unitario = precio base israelí de reforma (ILS) × coeficiente de categoría ÷ tipo de cambio, más 15 % de gastos generales y beneficio. Los coeficientes se calibraron con las referencias siguientes (tabiques, solados, puntos eléctricos, pintura, andamio); los oficios sin referencia usan la media. Coeficientes: part=0.37, tile=0.35, elec=0.53, paint=0.56, conc=0.55, scaf=1.15, gen=0.54. FX 3.5 ILS/EUR.
A12: Salvedades: fuentes mayoritariamente comerciales, rangos amplios y algunos sin fecha; no se usó ninguna base de precios oficial. Faltan datos de 2026 para tabiques, solados, hormigón y andamio en parte de las fuentes (hay resultados de otros países que se descartaron). Piscina: estimación propia con datos antiguos; el cerramiento de seguridad es una estimación sin fuente. La obra está en Haifa (Israel) – precios de referencia del mercado español, sin ajustar a las condiciones locales. Verificar con presupuestos de proveedores antes de presentar.
