Workbook

Sheet Devis
A1: DEVIS — Rénovation et extension, 53 rue Shlonsky, Haïfa
A2: Maître d'ouvrage : Zohar Mor Yosef et Rami Dana | Entreprise : [Nom de l'entreprise] | Date : 14/10/2026 | Devis n° : [__]
A3: Tous les montants en EUR (€), hors TVA, base de prix octobre 2026. Les prix unitaires incluent les frais généraux et la marge de l'entreprise (15 %).
A5: Poste | B5: Désignation | C5: Description | D5: Unité | E5: Qté | F5: Prix unitaire | G5: Montant | H5: Remarques
A6: Chapitre 1 — Préparation et installation de chantier
A7: 01.01 | B7: Installation de chantier | C7: Mise en place des zones de travail et de stockage, des installations du personnel et coordination des accès. | D7: forfait | E7: 1 | F7: 2210 | G7: =IF(AND(ISNUMBER(E7),ISNUMBER(F7)),ROUND(E7*F7,2),"") -> 2210
A8: 01.02 | B8: Clôture, signalisation et sécurité du chantier | C8: Clôture provisoire, panneaux de chantier et de danger, et mesures de sécurité requises pendant les travaux. | D8: forfait | E8: 1 | F8: 1100 | G8: =IF(AND(ISNUMBER(E8),ISNUMBER(F8)),ROUND(E8*F8,2),"") -> 1100
A9: 01.03 | B9: Branchement d'eau provisoire | C9: Branchement d'eau provisoire depuis la source agréée, avec essai. | D9: forfait | E9: 1 | F9: 414 | G9: =IF(AND(ISNUMBER(E9),ISNUMBER(F9)),ROUND(E9*F9,2),"") -> 414
A10: 01.04 | B10: Branchement électrique provisoire | C10: Branchement électrique provisoire réalisé par un électricien qualifié, avec protections et essais. | D10: forfait | E10: 1 | F10: 830 | G10: =IF(AND(ISNUMBER(E10),ISNUMBER(F10)),ROUND(E10*F10,2),"") -> 830
A11: 01.05 | B11: Protection des éléments existants | C11: Protections des sols, ouvertures, fenêtres, escaliers, garde-corps, murs et végétaux à conserver. | D11: forfait | E11: 1 | F11: 1380 | G11: =IF(AND(ISNUMBER(E11),ISNUMBER(F11)),ROUND(E11*F11,2),"") -> 1380
A12: 01.06 | B12: Relevés, vérification et traçage laser | C12: Relevé du bâti existant, vérification par rapport aux plans d'architecture et des lots techniques, traçage des positions et des niveaux. | D12: forfait | E12: 1 | F12: 830 | G12: =IF(AND(ISNUMBER(E12),ISNUMBER(F12)),ROUND(E12*F12,2),"") -> 830
A13: 01.07 | B13: Benne à déchets et zone de collecte | C13: Mise en place d'une benne et d'une zone de collecte ; évacuation des déchets vers un site agréé. | D13: forfait | E13: 1 | F13: 2480 | G13: =IF(AND(ISNUMBER(E13),ISNUMBER(F13)),ROUND(E13*F13,2),"") -> 2480
A14: 01.08 | B14: Nettoyage courant du chantier | C14: Nettoyage périodique des zones de travail et des circulations pendant toute la durée des travaux. | D14: forfait | E14: 1 | F14: 2480 | G14: =IF(AND(ISNUMBER(E14),ISNUMBER(F14)),ROUND(E14*F14,2),"") -> 2480
A15: 01.09 | B15: Échafaudage extérieur | C15: Montage, location pour la durée des travaux (environ 4,5 mois), entretien et démontage d'un échafaudage extérieur conforme autour des façades, pour le sciage des cadres en béton décoratifs et les travaux d'enduit de façade. | D15: m² | E15: 225 | F15: 40 | G15: =IF(AND(ISNUMBER(E15),ISNUMBER(F15)),ROUND(E15*F15,2),"") -> 9000 | H15: Quantité provisoire – métrée sur place
A16: Total – Chapitre 1 | G16: =IF(COUNT(G7:G15)=0,"",SUM(G7:G15)) -> 20724
A18: Chapitre 2 — Démolition, dépose et évacuation
A19: 02.01 | B19: Démolition de murs et cloisons – sous-sol | C19: Démolition des murs et cloisons existants selon les plans de démolition. | D19: m² | E19: 62 | F19: 33 | G19: =IF(AND(ISNUMBER(E19),ISNUMBER(F19)),ROUND(E19*F19,2),"") -> 2046
A20: 02.02 | B20: Démolition de murs et cloisons – rez-de-chaussée | C20: Démolition des murs et cloisons existants selon les plans de démolition. | D20: m² | E20: 51 | F20: 33 | G20: =IF(AND(ISNUMBER(E20),ISNUMBER(F20)),ROUND(E20*F20,2),"") -> 1683
A21: 02.03 | B21: Démolition de murs et cloisons – 1er étage | C21: Démolition des murs et cloisons existants selon les plans de démolition. | D21: m² | E21: 85 | F21: 33 | G21: =IF(AND(ISNUMBER(E21),ISNUMBER(F21)),ROUND(E21*F21,2),"") -> 2805
A22: 02.04 | B22: Dépose des faux plafonds en plaques de plâtre | C22: Dépose des faux plafonds en plaques de plâtre existants. | D22: m² | E22: 10 | F22: 14 | G22: =IF(AND(ISNUMBER(E22),ISNUMBER(F22)),ROUND(E22*F22,2),"") -> 140
A23: 02.05 | B23: Dépose des revêtements de sol existants | C23: Dépose des revêtements de sol existants. | D23: m² | E23: 40 | F23: 25 | G23: =IF(AND(ISNUMBER(E23),ISNUMBER(F23)),ROUND(E23*F23,2),"") -> 1000
A24: 02.06 | B24: Dépose des meubles de cuisine existants | C24: Dépose complète des meubles de cuisine existants. | D24: forfait | E24: 1 | F24: 550 | G24: =IF(AND(ISNUMBER(E24),ISNUMBER(F24)),ROUND(E24*F24,2),"") -> 550
A25: 02.07 | B25: Dépose des autres meubles et menuiseries | C25: Dépose des autres meubles et ouvrages de menuiserie existants. | D25: u | E25: 1 | F25: 690 | G25: =IF(AND(ISNUMBER(E25),ISNUMBER(F25)),ROUND(E25*F25,2),"") -> 690
A26: 02.08 | B26: Dépose des fenêtres aluminium et volets roulants existants | C26: Dépose complète des fenêtres en aluminium et des volets roulants existants. | D26: forfait | E26: 1 | F26: 1660 | G26: =IF(AND(ISNUMBER(E26),ISNUMBER(F26)),ROUND(E26*F26,2),"") -> 1660
A27: 02.09 | B27: Dépose des portes intérieures et d'entrée et de leurs huisseries | C27: Dépose complète des portes intérieures et d'entrée et de leurs huisseries. | D27: forfait | E27: 1 | F27: 970 | G27: =IF(AND(ISNUMBER(E27),ISNUMBER(F27)),ROUND(E27*F27,2),"") -> 970
A28: 02.10 | B28: Dépose des salles de bains, WC et appareils sanitaires | C28: Dépose complète des salles de bains, WC et appareils sanitaires existants. | D28: forfait | E28: 1 | F28: 2210 | G28: =IF(AND(ISNUMBER(E28),ISNUMBER(F28)),ROUND(E28*F28,2),"") -> 2210
A29: 02.11 | B29: Dépose des points, appareillages et luminaires électriques | C29: Dépose des points électriques, appareillages et luminaires existants. | D29: forfait | E29: 1 | F29: 1100 | G29: =IF(AND(ISNUMBER(E29),ISNUMBER(F29)),ROUND(E29*F29,2),"") -> 1100
A30: 02.12 | B30: Dépose des canalisations apparentes existantes | C30: Dépose des canalisations de plomberie apparentes existantes. | D30: forfait | E30: 1 | F30: 830 | G30: =IF(AND(ISNUMBER(E30),ISNUMBER(F30)),ROUND(E30*F30,2),"") -> 830
... A38: 02.20 | B38: Dépose de l'escalier d'entrée existant | C38: Dépose de l'escalier d'entrée existant, y compris découpe, chargement et évacuation, avant la réalisation des nouvelles marches suspendues. | D38: forfait | E38: 1 | F38: 830 | G38: =IF(AND(ISNUMBER(E38),ISNUMBER(F38)),ROUND(E38*F38,2),"") -> 830
A39: 02.21 | B39: Dépose du gazon et des plantations | C39: Dépose du gazon, arbustes et plantations existants dans les zones aménagées, y compris racines, chargement et évacuation. | D39: m² | E39: 65 | F39: 9.7 | G39: =IF(AND(ISNUMBER(E39),ISNUMBER(F39)),ROUND(E39*F39,2),"") -> 630.5 | H39: Quantité provisoire – métrée sur place
A40: Total – Chapitre 2 | G40: =IF(COUNT(G19:G39)=0,"",SUM(G19:G39)) -> 33221.1
A42: Chapitre 3 — Travaux de structure et extensions
A43: 03.01 | B43: Agrandissement du balcon du salon et nouvelle pergola | C43: Travaux de structure complets selon les plans et le cahier des charges de l'ingénieur structure. | D43: forfait | E43: 1 | F43: 19300 | G43: =IF(AND(ISNUMBER(E43),ISNUMBER(F43)),ROUND(E43*F43,2),"") -> 19300 | H43: Forfait – ajusté à réception des plans de structure
A44: 03.02 | B44: Nouvelle pièce au niveau de la galerie | C44: Travaux de structure complets de la pièce selon les plans de structure et d'architecture, y compris liaisons avec l'existant et réservations. Finitions et lots techniques dans leurs chapitres. | D44: forfait | E44: 1 | F44: 33100 | G44: =IF(AND(ISNUMBER(E44),ISNUMBER(F44)),ROUND(E44*F44,2),"") -> 33100 | H44: Forfait – ajusté à réception des plans de structure
A45: 03.03 | B45: Nouvelle entrée et nouvel escalier | C45: Travaux complets de la nouvelle entrée et de l'escalier selon l'ingénieur structure. | D45: forfait | E45: 1 | F45: 10500 | G45: =IF(AND(ISNUMBER(E45),ISNUMBER(F45)),ROUND(E45*F45,2),"") -> 10500 | H45: Forfait – ajusté à réception des plans de structure
A46: 03.04 | B46: Renforcement de l'escalier intérieur existant | C46: Renforcement selon l'ingénieur structure, après dépose du garde-corps. | D46: forfait | E46: 1 | F46: 4970 | G46: =IF(AND(ISNUMBER(E46),ISNUMBER(F46)),ROUND(E46*F46,2),"") -> 4970 | H46: Forfait – ajusté à réception des plans de structure
A47: 03.05 | B47: Marches d'entrée suspendues | C47: 12 nouvelles marches suspendues (en console) à l'entrée, en remplacement de l'escalier existant, largeur d'environ 1,15 m, y compris ferraillage, ancrages et préparation au revêtement, selon plans de structure et d'architecture. Revêtement au poste 13.08. | D47: u | E47: 12 | F47: 770 | G47: =IF(AND(ISNUMBER(E47),ISNUMBER(F47)),ROUND(E47*F47,2),"") -> 9240 | H47: Forfait – ajusté à réception des plans de structure; Dimension définitive selon l'existant sur place
A48: Total – Chapitre 3 | G48: =IF(COUNT(G43:G47)=0,"",SUM(G43:G47)) -> 77110
A50: Chapitre 4 — Nouveaux murs en blocs
A51: 04.01 | B51: Nouveaux murs en blocs (20 cm) – sous-sol | C51: Murs en blocs selon plans. | D51: m² | E51: 6.3 | F51: 83 | G51: =IF(AND(ISNUMBER(E51),ISNUMBER(F51)),ROUND(E51*F51,2),"") -> 522.9
A52: 04.02 | B52: Nouveaux murs en blocs (20 cm) – rez-de-chaussée | C52: Murs en blocs selon plans. | D52: m² | E52: 17.7 | F52: 83 | G52: =IF(AND(ISNUMBER(E52),ISNUMBER(F52)),ROUND(E52*F52,2),"") -> 1469.1
A53: 04.03 | B53: Nouveaux murs en blocs (20 cm) – 1er étage et galerie | C53: Murs en blocs selon plans. | D53: m² | E53: 2.08 | F53: 83 | G53: =IF(AND(ISNUMBER(E53),ISNUMBER(F53)),ROUND(E53*F53,2),"") -> 172.64
A54: Total – Chapitre 4 | G54: =IF(COUNT(G51:G53)=0,"",SUM(G51:G53)) -> 2164.64
A56: Chapitre 5 — Plomberie, appareils sanitaires et robinetterie
A57: 05.01 | B57: Cuvette de WC suspendue | C57: Pose, fixation au bâti-support, raccordement à la chasse et à l'évacuation, et essais. | D57: u | E57: 7 | F57: 221 | G57: =IF(AND(ISNUMBER(E57),ISNUMBER(F57)),ROUND(E57*F57,2),"") -> 1547 | H57: Pose uniquement ; fourniture par le maître d'ouvrage
A58: 05.02 | B58: Réservoir encastré et bâti-support | C58: Pose, ancrage, raccordement à l'eau et au WC, et essai d'étanchéité avant fermeture du doublage. | D58: u | E58: 7 | F58: 304 | G58: =IF(AND(ISNUMBER(E58),ISNUMBER(F58)),ROUND(E58*F58,2),"") -> 2128 | H58: Pose uniquement ; fourniture par le maître d'ouvrage
A59: 05.03 | B59: Plaque de commande de chasse | C59: Pose de la plaque compatible avec le réservoir encastré et essai. | D59: u | E59: 7 | F59: 41.5 | G59: =IF(AND(ISNUMBER(E59),ISNUMBER(F59)),ROUND(E59*F59,2),"") -> 290.5 | H59: Pose uniquement ; fourniture par le maître d'ouvrage
A60: 05.04 | B60: Abattant de WC à fermeture amortie | C60: Pose et réglage. | D60: u | E60: 7 | F60: 41.5 | G60: =IF(AND(ISNUMBER(E60),ISNUMBER(F60)),ROUND(E60*F60,2),"") -> 290.5 | H60: Pose uniquement ; fourniture par le maître d'ouvrage
A61: 05.05 | B61: Lavabo sur pied | C61: Pose, fixation, raccordement à l'évacuation et étanchéité. | D61: u | E61: 1 | F61: 166 | G61: =IF(AND(ISNUMBER(E61),ISNUMBER(F61)),ROUND(E61*F61,2),"") -> 166 | H61: Pose uniquement ; fourniture par le maître d'ouvrage
A62: 05.06 | B62: Robinet mural | C62: Pose et raccordement. | D62: u | E62: 6 | F62: 83 | G62: =IF(AND(ISNUMBER(E62),ISNUMBER(F62)),ROUND(E62*F62,2),"") -> 498 | H62: Pose uniquement ; fourniture par le maître d'ouvrage
A63: 05.07 | B63: Pomme de douche pluie | C63: Pose et raccordement. | D63: u | E63: 6 | F63: 124 | G63: =IF(AND(ISNUMBER(E63),ISNUMBER(F63)),ROUND(E63*F63,2),"") -> 744 | H63: Pose uniquement ; fourniture par le maître d'ouvrage
A64: 05.08 | B64: Inverseur 3 voies | C64: Pose de l'inverseur 3 voies (type Interpoz) et de sa finition. | D64: u | E64: 10 | F64: 124 | G64: =IF(AND(ISNUMBER(E64),ISNUMBER(F64)),ROUND(E64*F64,2),"") -> 1240 | H64: Pose uniquement ; fourniture par le maître d'ouvrage
A65: 05.09 | B65: Inverseur 4 voies | C65: Pose de l'inverseur 4 voies (type Interpoz) et de sa finition. | D65: u | E65: 2 | F65: 166 | G65: =IF(AND(ISNUMBER(E65),ISNUMBER(F65)),ROUND(E65*F65,2),"") -> 332 | H65: Pose uniquement ; fourniture par le maître d'ouvrage
A66: 05.10 | B66: Support de douchette | C66: Pose du support de douchette. | D66: u | E66: 7 | F66: 69 | G66: =IF(AND(ISNUMBER(E66),ISNUMBER(F66)),ROUND(E66*F66,2),"") -> 483 | H66: Pose uniquement ; fourniture par le maître d'ouvrage
A67: 05.11 | B67: Caniveau de douche linéaire 10/10 | C67: Pose et raccordement du caniveau. | D67: u | E67: 5 | F67: 179 | G67: =IF(AND(ISNUMBER(E67),ISNUMBER(F67)),ROUND(E67*F67,2),"") -> 895 | H67: Pose uniquement ; fourniture par le maître d'ouvrage
A68: 05.12 | B68: Trop-plein 110 pour baignoire | C68: Pose du trop-plein. | D68: u | E68: 1 | F68: 414 | G68: =IF(AND(ISNUMBER(E68),ISNUMBER(F68)),ROUND(E68*F68,2),"") -> 414 | H68: Pose uniquement ; fourniture par le maître d'ouvrage
... A70: 05.15 | B70: Robinet de remplissage de baignoire | C70: Pose du robinet de remplissage. | D70: u | E70: 1 | F70: 276 | G70: =IF(AND(ISNUMBER(E70),ISNUMBER(F70)),ROUND(E70*F70,2),"") -> 276 | H70: Pose uniquement ; fourniture par le maître d'ouvrage
A71: 05.16 | B71: Évier de cuisine | C71: Posé par le fournisseur du plan de travail. | D71: u | E71: 3 | F71: Par le fournisseur du plan de travail | G71: =IF(AND(ISNUMBER(E71),ISNUMBER(F71)),ROUND(E71*F71,2),"")
A72: 05.17 | B72: Mitigeur de cuisine à douchette extractible | C72: Pose, raccordement et essai de fonctionnement. | D72: u | E72: 5 | F72: 124 | G72: =IF(AND(ISNUMBER(E72),ISNUMBER(F72)),ROUND(E72*F72,2),"") -> 620 | H72: Pose uniquement ; fourniture par le maître d'ouvrage
A73: 05.18 | B73: Évier de cuisine extérieure | C73: Posé par le fournisseur du plan de travail. | D73: u | E73: 2 | F73: Par le fournisseur du plan de travail | G73: =IF(AND(ISNUMBER(E73),ISNUMBER(F73)),ROUND(E73*F73,2),"")
A74: 05.19 | B74: Mitigeur extérieur à douchette extractible | C74: Pose et raccordement. | D74: u | E74: 2 | F74: 124 | G74: =IF(AND(ISNUMBER(E74),ISNUMBER(F74)),ROUND(E74*F74,2),"") -> 248 | H74: Pose uniquement ; fourniture par le maître d'ouvrage
A75: 05.20 | B75: Vasque à poser / auge – WC invités | C75: Pose et raccordement. | D75: u | E75: 1 | F75: 179 | G75: =IF(AND(ISNUMBER(E75),ISNUMBER(F75)),ROUND(E75*F75,2),"") -> 179 | H75: Pose uniquement ; fourniture par le maître d'ouvrage
A76: 05.21 | B76: Robinet « Nil » | C76: Pose du robinet. | D76: u | E76: 11 | F76: 49.5 | G76: =IF(AND(ISNUMBER(E76),ISNUMBER(F76)),ROUND(E76*F76,2),"") -> 544.5 | H76: Pose uniquement ; fourniture par le maître d'ouvrage
A77: 05.22 | B77: Robinet avec meuble vasque – ensemble | C77: Pose du robinet et du meuble vasque en ensemble. | D77: u | E77: 1 | F77: 497 | G77: =IF(AND(ISNUMBER(E77),ISNUMBER(F77)),ROUND(E77*F77,2),"") -> 497 | H77: Pose uniquement ; fourniture par le maître d'ouvrage
A78: 05.23 | B78: Caniveau de débordement extérieur 60 | C78: Pose du caniveau de débordement extérieur. | D78: u | E78: 1 | F78: 331 | G78: =IF(AND(ISNUMBER(E78),ISNUMBER(F78)),ROUND(E78*F78,2),"") -> 331 | H78: Pose uniquement ; fourniture par le maître d'ouvrage
A79: 05.24 | B79: Évier de bar | C79: Pose et raccordement. | D79: u | E79: 2 | F79: 152 | G79: =IF(AND(ISNUMBER(E79),ISNUMBER(F79)),ROUND(E79*F79,2),"") -> 304 | H79: Pose uniquement ; fourniture par le maître d'ouvrage
A80: 05.25 | B80: Point d'eau chaude et froide | C80: Alimentation et point d'eau. | D80: pt | E80: 23 | F80: 331 | G80: =IF(AND(ISNUMBER(E80),ISNUMBER(F80)),ROUND(E80*F80,2),"") -> 7613
A81: 05.26 | B81: Point d'eau froide pour réservoir de chasse | C81: Alimentation et point d'eau. | D81: pt | E81: 7 | F81: 138 | G81: =IF(AND(ISNUMBER(E81),ISNUMBER(F81)),ROUND(E81*F81,2),"") -> 966
A82: 05.27 | B82: Point d'évacuation pour WC | C82: Évacuation et point de raccordement. | D82: pt | E82: 7 | F82: 193 | G82: =IF(AND(ISNUMBER(E82),ISNUMBER(F82)),ROUND(E82*F82,2),"") -> 1351
A83: 05.28 | B83: Point d'évacuation lavabo et baignoire | C83: Évacuation et point de raccordement. | D83: pt | E83: 15 | F83: 124 | G83: =IF(AND(ISNUMBER(E83),ISNUMBER(F83)),ROUND(E83*F83,2),"") -> 1860
A84: 05.29 | B84: Point d'eau et d'évacuation pour lave-linge | C84: Alimentation et évacuation. | D84: pt | E84: 2 | F84: 248 | G84: =IF(AND(ISNUMBER(E84),ISNUMBER(F84)),ROUND(E84*F84,2),"") -> 496
A85: 05.30 | B85: Robinet de service | C85: Pose du robinet de service. | D85: u | E85: 2 | F85: 49.5 | G85: =IF(AND(ISNUMBER(E85),ISNUMBER(F85)),ROUND(E85*F85,2),"") -> 99
A86: 05.32 | B86: Colonnes d'alimentation et nourrices d'étage | C86: Alimentation principale en eau et nourrices par niveau. | D86: forfait | E86: 1 | F86: 5500 | G86: =IF(AND(ISNUMBER(E86),ISNUMBER(F86)),ROUND(E86*F86,2),"") -> 5500
A87: 05.33 | B87: Réseau principal d'assainissement | C87: Réseau principal d'assainissement et d'évacuation. | D87: forfait | E87: 1 | F87: 4970 | G87: =IF(AND(ISNUMBER(E87),ISNUMBER(F87)),ROUND(E87*F87,2),"") -> 4970
A88: 05.34 | B88: Chauffe-eau – pose et raccordement | C88: Pose et raccordement du chauffe-eau. | D88: u | E88: 1 | F88: 331 | G88: =IF(AND(ISNUMBER(E88),ISNUMBER(F88)),ROUND(E88*F88,2),"") -> 331 | H88: Pose uniquement ; fourniture par le maître d'ouvrage
A89: 05.35 | B89: Essais de pression et d'étanchéité, plans de récolement | C89: Essais des installations de plomberie et dossier de récolement. | D89: forfait | E89: 1 | F89: 690 | G89: =IF(AND(ISNUMBER(E89),ISNUMBER(F89)),ROUND(E89*F89,2),"") -> 690
A90: Total – Chapitre 5 | G90: =IF(COUNT(G57:G89)=0,"",SUM(G57:G89)) -> 36513.5
A92: Chapitre 6 — Électricité
A93: 06.01 | B93: Point de prise courante | C93: Câblage sur le circuit concerné, appareillage et essai. | D93: u | E93: 119 | F93: 113 | G93: =IF(AND(ISNUMBER(E93),ISNUMBER(F93)),ROUND(E93*F93,2),"") -> 13447
A94: 06.02 | B94: Point de prise étanche | C94: Point de prise étanche (IP44 ou plus). | D94: u | E94: 51 | F94: 134 | G94: =IF(AND(ISNUMBER(E94),ISNUMBER(F94)),ROUND(E94*F94,2),"") -> 6834
A95: 06.03 | B95: Alimentation pour volet roulant électrique | C95: Gaines et câblage pour la commande du volet électrique. | D95: u | E95: 18 | F95: 159 | G95: =IF(AND(ISNUMBER(E95),ISNUMBER(F95)),ROUND(E95*F95,2),"") -> 2862
A96: 06.05 | B96: Point de prise triphasée | C96: Point de prise triphasée. | D96: u | E96: 1 | F96: 376 | G96: =IF(AND(ISNUMBER(E96),ISNUMBER(F96)),ROUND(E96*F96,2),"") -> 376
A97: 06.06 | B97: Extension du tableau électrique principal | C97: Extension du tableau principal pour la charge totale ajoutée. | D97: forfait | E97: 1 | F97: 2350 | G97: =IF(AND(ISNUMBER(E97),ISNUMBER(F97)),ROUND(E97*F97,2),"") -> 2350
A98: 06.07 | B98: Pilier du fournisseur d'électricité – fourniture et pose | C98: Fourniture et pose du nouveau pilier du fournisseur d'électricité à l'entrée du terrain. | D98: forfait | E98: 1 | F98: 1930 | G98: =IF(AND(ISNUMBER(E98),ISNUMBER(F98)),ROUND(E98*F98,2),"") -> 1930
A99: 06.09 | B99: Contrôle électrique final | C99: Contrôle final par un organisme agréé, attestation et rapport d'essais. | D99: forfait | E99: 1 | F99: 690 | G99: =IF(AND(ISNUMBER(E99),ISNUMBER(F99)),ROUND(E99*F99,2),"") -> 690
A100: 06.10 | B100: Point de prise de force | C100: Point de prise de force. | D100: u | E100: 9 | F100: 159 | G100: =IF(AND(ISNUMBER(E100),ISNUMBER(F100)),ROUND(E100*F100,2),"") -> 1431
A101: 06.11 | B101: Alimentation dédiée pour unité de climatisation | C101: Alimentation dédiée pour une unité de climatisation. | D101: pt | E101: 8 | F101: 313 | G101: =IF(AND(ISNUMBER(E101),ISNUMBER(F101)),ROUND(E101*F101,2),"") -> 2504
A102: 06.12 | B102: Raccordement direct au tableau – plaque de cuisson, four et appareils dédiés | C102: Raccordement direct au tableau sur ligne dédiée avec protection séparée pour chaque appareil (plaque, four, lave-vaisselle, sèche-linge et autres), y compris câble, gaine, raccordement final et essais. | D102: forfait | E102: 1 | F102: 1460 | G102: =IF(AND(ISNUMBER(E102),ISNUMBER(F102)),ROUND(E102*F102,2),"") -> 1460
A103: 06.13 | B103: Interrupteur de chauffe-eau avec voyant | C103: Interrupteur de chauffe-eau avec voyant lumineux. | D103: u | E103: 1 | F103: 146 | G103: =IF(AND(ISNUMBER(E103),ISNUMBER(F103)),ROUND(E103*F103,2),"") -> 146
A104: Total – Chapitre 6 | G104: =IF(COUNT(G93:G103)=0,"",SUM(G93:G103)) -> 34030
A106: Chapitre 7 — Éclairage et interrupteurs
A107: 07.01 | B107: Interrupteurs d'éclairage (simples) | C107: Pose des interrupteurs d'éclairage. | D107: u | E107: 62 | F107: 63 | G107: =IF(AND(ISNUMBER(E107),ISNUMBER(F107)),ROUND(E107*F107,2),"") -> 3906
A108: 07.02 | B108: Interrupteurs va-et-vient | C108: Pose des interrupteurs va-et-vient. | D108: u | E108: 16 | F108: 83 | G108: =IF(AND(ISNUMBER(E108),ISNUMBER(F108)),ROUND(E108*F108,2),"") -> 1328
A109: 07.02a | B109: Permutateur (interrupteur de croisement) | C109: Pose d'un permutateur sur un circuit d'éclairage commandé de trois points ou plus, entre les va-et-vient, y compris appareillage, câblage intermédiaire et essais. | D109: u | E109: 3 | F109: 100 | G109: =IF(AND(ISNUMBER(E109),ISNUMBER(F109)),ROUND(E109*F109,2),"") -> 300
A110: 07.03 | B110: Luminaire de plafond en applique | C110: Pose, raccordement électrique et essai. | D110: u | E110: 15 | F110: 92 | G110: =IF(AND(ISNUMBER(E110),ISNUMBER(F110)),ROUND(E110*F110,2),"") -> 1380 | H110: Pose uniquement ; fourniture par le maître d'ouvrage
A111: 07.04 | B111: Luminaire suspendu | C111: Pose, système de suspension, réglage de la hauteur selon plan, raccordement et essai. | D111: u | E111: 22 | F111: 134 | G111: =IF(AND(ISNUMBER(E111),ISNUMBER(F111)),ROUND(E111*F111,2),"") -> 2948 | H111: Pose uniquement ; fourniture par le maître d'ouvrage
A112: 07.05 | B112: Applique murale protégée | C112: Pose et raccordement. | D112: u | E112: 30 | F112: 92 | G112: =IF(AND(ISNUMBER(E112),ISNUMBER(F112)),ROUND(E112*F112,2),"") -> 2760 | H112: Pose uniquement ; fourniture par le maître d'ouvrage
A113: 07.06 | B113: Luminaire mural encastré protégé | C113: Pose et raccordement. | D113: u | E113: 35 | F113: 125 | G113: =IF(AND(ISNUMBER(E113),ISNUMBER(F113)),ROUND(E113*F113,2),"") -> 4375 | H113: Pose uniquement ; fourniture par le maître d'ouvrage
A114: 07.07 | B114: Spot encastré en faux plafond | C114: Pose et raccordement. | D114: u | E114: 25 | F114: 35.5 | G114: =IF(AND(ISNUMBER(E114),ISNUMBER(F114)),ROUND(E114*F114,2),"") -> 887.5 | H114: Pose uniquement ; fourniture par le maître d'ouvrage
A115: 07.08 | B115: Ruban LED dissimulé | C115: Pose du ruban LED dissimulé. | D115: u | E115: 11 | F115: 146 | G115: =IF(AND(ISNUMBER(E115),ISNUMBER(F115)),ROUND(E115*F115,2),"") -> 1606 | H115: Pose uniquement ; fourniture par le maître d'ouvrage
...

Sheet Récapitulatif
A1: Récapitulatif du devis
A3: Chapitre | B3: Montant | C3: % du total
A4: 1. Préparation et installation de chantier | B4: ='Devis'!G16 -> 20724 | C4: =IF($B$17=0,0,B4/$B$17) -> 0.057311627
A5: 2. Démolition, dépose et évacuation | B5: ='Devis'!G40 -> 33221.1 | C5: =IF($B$17=0,0,B5/$B$17) -> 0.091871998
A6: 3. Travaux de structure et extensions | B6: ='Devis'!G48 -> 77110 | C6: =IF($B$17=0,0,B6/$B$17) -> 0.21324549
A7: 4. Nouveaux murs en blocs | B7: ='Devis'!G54 -> 2164.64 | C7: =IF($B$17=0,0,B7/$B$17) -> 0.0059862497
A8: 5. Plomberie, appareils sanitaires et robinetterie | B8: ='Devis'!G90 -> 36513.5 | C8: =IF($B$17=0,0,B8/$B$17) -> 0.10097704
A9: 6. Électricité | B9: ='Devis'!G104 -> 34030 | C9: =IF($B$17=0,0,B9/$B$17) -> 0.094108988
A10: 7. Éclairage et interrupteurs | B10: ='Devis'!G126 -> 36028 | C10: =IF($B$17=0,0,B10/$B$17) -> 0.099634399
A11: 9. Cloisons et plafonds en plaques de plâtre | B11: ='Devis'!G133 -> 8264.85 | C11: =IF($B$17=0,0,B11/$B$17) -> 0.022856205
A12: 10. Étanchéité intérieure | B12: ='Devis'!G139 -> 8839.9 | C12: =IF($B$17=0,0,B12/$B$17) -> 0.02444649
A13: 12. Appuis de fenêtre et calfeutrement | B13: ='Devis'!G145 -> 4719.18 | C13: =IF($B$17=0,0,B13/$B$17) -> 0.013050757
A14: 13. Sols, faïence et revêtements | B14: ='Devis'!G155 -> 40750.85 | C14: =IF($B$17=0,0,B14/$B$17) -> 0.11269531
A15: 14. Enduits, lissage et peinture | B15: ='Devis'!G161 -> 39546 | C15: =IF($B$17=0,0,B15/$B$17) -> 0.10936333
A16: 17. Aménagements extérieurs | B16: ='Devis'!G169 -> 19690 | C16: =IF($B$17=0,0,B16/$B$17) -> 0.054452129
A17: Total HT | B17: =SUM(B4:B16) -> 361602.02
A18: TVA (20%) | B18: ='Devis'!G172 -> 72320.4
A19: TOTAL TTC | B19: =B17+B18 -> 433922.42

Sheet Conditions et exclusions
A1: # | B1: Conditions et exclusions
A2: 1 | B2: Base du devis | C2: Le devis repose sur le cahier des charges techniques (révision 20, 06/07/2026), les plans d'architecture « Construction neuve » – rez-de-chaussée et 1er étage (17/09/2026) et le bordereau de quantités de l'entreprise du 24/09/2026. En cas de divergence, le bordereau du 24/09/2026 prévaut.
A3: 2 | B3: Quantités | C3: Quantités selon les documents ci-dessus. Les postes « provisoires » ou « selon métré sur place » seront métrés ; le décompte final suit les quantités réellement exécutées.
A4: 3 | B4: Structure | C4: Le chapitre 3 (balcon et pergola, pièce en galerie, entrée et escalier, renforcement de l'escalier intérieur) est un forfait selon les plans de l'ingénieur structure ; le prix sera ajusté à réception des plans de structure complets.
A5: 4 | B5: Fournitures | C5: Appareils sanitaires et robinetterie, luminaires, unités de climatisation, chauffe-eau et carreaux de sol et muraux sont fournis par le maître d'ouvrage ; l'entreprise les pose. Les éviers de cuisine sont posés par le fournisseur du plan de travail.
A6: 5 | B6: Exclusions | C6: Piscine ; menuiserie (meubles de cuisine, de salle de bains et dressings) ; fenêtres et portes en aluminium, portes intérieures et d'entrée, portails et volets ; travaux d'acrotère ; mobilier ; permis et taxes ; honoraires des consultants (structure, étanchéité, éclairage) ; frais du fournisseur d'électricité pour l'augmentation de puissance.
A7: 6 | B7: Essais | C7: Les essais et approbations requis (ingénieur structure, bureau d'étanchéité, contrôleur électrique agréé, essais de mise en eau et de pression) sont inclus.
A8: 7 | B8: Prix | C8: Prix en EUR, hors TVA, base octobre 2026, sans révision sauf accord contraire.
A9: 8 | B9: Conditions commerciales | C9: Validité : [__ jours] | Conditions de paiement : [__] | Planning : [__]

Sheet Étude de marché (interne)
A1: Catégorie | B1: Données de marché trouvées (2026) | C1: Sources
A2: Cloison en plaques de plâtre | B2: 27–41 €/m² HT (standard) ; hydrofuge 30–45 ; isolant 38–60 | C2: prix-travaux-m2.com/prix-cloison-placo.php (janv. 2026) ; habitatpresto.com/mag/renovation/cloison-placo/tarif-plaquiste
A3: Pose de carrelage grand format | B3: 120×120 : 50–60 €/m² posé, fourniture comprise (page datée juil. 2025) ; main-d'œuvre seule : référence belge 25–55 €/m² | C3: prix-travaux-m2.com/prix-pose-carrelage.php ; blog.trustup.be/fr/?p=1107 (Belgique)
A4: Point électrique / prise | B4: Aucun tarif français trouvé ; référence belge 80–250 € pour une prise | C4: blog.trustup.be/fr/travaux/electricite/ (Belgique – indicatif)
A5: Peinture intérieure | B5: murs 20–48 €/m² HT, fournitures incluses ; plafonds 25–55 €/m² | C5: habitatpresto.com/mag/revetement/mur/dossier-peinture-interieure
A6: Allée en dalle béton | B6: 60–100 €/m² HT (allée carrossable 12–20 cm) ; 55–115 €/m² pose comprise | C6: prix-travaux-m2.com/prix-dalle-de-beton.php ; habitatpresto.com/mag/maconnerie/prix-dalle-beton
A7: Échafaudage | B7: pose 20–50 €/m² (indicatif, sans date) ; exemple belge 1 200 € HTVA pour 80 m² | C7: conseils.hellopro.fr/guide-de-prix-des-echafaudages-1212.html ; blog.trustup.be/fr/prix-renovation-facade/
A8: Taux de change | B8: ≈ 3,50 ILS pour 1 EUR (≈ 3,46 début août 2026 ; valeurs d'octobre = prévisions) | C8: ofx.com/en-au/exchange-rates/eur-to-ils/ ; b-sharpe.com
A10: Méthode : chaque prix unitaire = prix de base israélien de rénovation (ILS) × coefficient de catégorie ÷ taux de change, puis + 15 % de frais généraux et marge. Les coefficients ont été calés sur les repères ci-dessous (cloisons, carrelage, points électriques, peinture, dalle béton, échafaudage) ; les corps d'état sans repère utilisent la moyenne des coefficients calés. Coefficients : part=0.41, tile=0.5, elec=1.27, paint=1.4, conc=0.7, scaf=1.44, gen=0.84. FX 3.5 ILS/EUR.
A11: Réserves : sources majoritairement commerciales, fourchettes larges et parfois sans date ; aucun bordereau officiel utilisé. Aucun tarif français pour les points électriques (référence belge). Le chantier est à Haïfa (Israël) – prix de référence du marché français, non ajustés aux conditions locales. À vérifier avec des devis fournisseurs avant remise.
